{
    "queries": {
        "b3c2606c-0943-41ee-b08a-d79feebfb14d": "What is the numeric value provided in the context information?",
        "51429fb0-516a-4a7d-a035-6984f7d236b2": "Describe the formatting of the context block around the numeric value, including any separators used.",
        "38a5a9f9-3307-4ce4-8122-6a3294fcf867": "\uac1d\uad00\uc2dd: \ub2e4\uc74c \uc911 \ubcf8 \ubb38\uc11c\uc5d0\uc11c \ubb34\uc120 \ud5c8\uac00\uc790\ub4e4\uc5d0\uac8c \uc778\uc13c\ud2f0\ube0c\ub97c \uc81c\uacf5\ud558\ub294 \uc8fc\ub41c \ubaa9\uc801\uc740 \ubb34\uc5c7\uc778\uac00?",
        "dae4fd20-ae84-41eb-bbfe-164c215208bf": "A) \ub3c4\uc2dc \uc9c0\uc5ed\uc758 \uc11c\ube44\uc2a4 \ud655\ub300",
        "9ff4a22d-763e-4d85-8239-594e55e05f27": "\ubb38\uc11c\uc5d0 \uc81c\uc2dc\ub41c \ub450 \uac00\uc9c0 \uc8fc\uc694 \ubaa9\ud45c\ub97c \uac01\uac01 \uac04\ub2e8\ud788 \uc124\uba85\ud558\uc2dc\uc624. (\uc608: AI\uac00 \uc0dd\uc131\ud55c \ucf58\ud150\uce20\ub97c \ud0d0\uc9c0\ud558\uace0 \uacf5\uc2dd \ucf58\ud150\uce20\ub97c \uc778\uc99d\ud558\uae30 \uc704\ud55c \ud45c\uc900\uacfc \ubaa8\ubc94\uc0ac\ub840 \ud655\ub9bd; \uc911\uc694 \uc18c\ud504\ud2b8\uc6e8\uc5b4\uc758 \ucde8\uc57d\uc810\uc744 \ucc3e\uc544 \uc218\uc815\ud560 \uc218 \uc788\ub294 AI \ud234 \uac1c\ubc1c\uc744 \uc704\ud55c \ud504\ub85c\uadf8\ub7a8 \uc218\ub9bd.)",
        "ab4a35c3-b515-4896-91f8-3415bfa7fa7a": "\ub2e4\uc74c \uc911 \ubbf8\uad6d \uc5f0\ubc29 \ucc28\uc6d0\uc758 \uac1c\uc778\uc815\ubcf4\ubcf4\ud638 \uc815\ucc45\uc5d0\uc11c \uc6b0\uc120\uc2dc\ub418\ub294 \uc870\uce58\ub85c \uc62c\ubc14\ub978 \uac83\uc744 \uace0\ub974\uc2dc\uc624.",
        "eaf8eb0e-9291-4cb2-9f9d-07deba2e8af5": "- Q1 (\ub2e4\uc9c0\uc120\ub2e4\ud615): \uc544\ub798 \uc911 \ubb38\uc11c\uc758 \ubaa9\ud45c\uc5d0 \ud3ec\ud568\ub418\uc9c0 \uc54a\ub294 \uac83\uc740 \ubb34\uc5c7\uc778\uac00?",
        "f75dd53a-296b-4aeb-bea5-22c354b8dae8": "A) AI \uad00\ub828 \uc758\ub8cc \ubd84\uc57c \uc704\ud5d8 \ubcf4\uace0 \uccb4\uacc4 \uc218\ub9bd\uacfc AI \uc9c0\uc6d0 \uad50\uc721 \ub3c4\uad6c \ubc30\ud3ec \uc9c0\uc6d0",
        "da98e0d4-d0c2-49e2-9aea-d8b41044dbc0": "\uac1d\uad00\uc2dd(\ub2e4\uc9c0\uc120\ub2e4\ud615): \ub2e4\uc74c \uc911 \uc774 \uc790\uae08\uc758 \ubcf4\uc870\uae08\uc744 \ubc30\ubd84\ud560 \uacc4\ud68d\uc744 \ubc1c\ud45c\ud55c \ubbf8\uad6d \ubd80\ucc98\ub294 \uc5b4\ub514\uc778\uac00?",
        "eb9354e3-9ba5-4e58-b485-0da5ff03f7cb": "A) \uc5d0\ub108\uc9c0\ubd80",
        "7823496a-eca4-4a2f-9790-02803c5b0e3e": "\ubcf8\ubb38\uc5d0 \ub530\ub974\uba74 \ub514\uc9c0\ud138 \ud2b8\uc708 \uae30\uc220\uc740 \uc804\ud22c \uc218\ud589\uc5d0\uc11c \uc5b4\ub5a4 \ubcc0\ud601\uc801 \uc7a0\uc7ac\ub825\uc744 \uc778\uc815\ubc1b\uace0 \uc788\uc73c\uba70, \uc774\ub97c \ud1b5\ud574 \uacf5\uae09\ub9dd \uad00\ub9ac \ubc0f \uc804\uc7a5 \ub2a5\ub825 \ud5a5\uc0c1\uc5d0 \uc5b4\ub5a4 \uc601\ud5a5\uc744 \ubbf8\uce60 \uc218 \uc788\ub294\uc9c0 \ub450 \uac00\uc9c0 \uce21\uba74\uc73c\ub85c \uc124\uba85\ud558\uc2dc\uc624.",
        "5b6847b5-fc21-4871-8b9f-99059a5bd716": "\ub2e4\uc74c \uc911 \ubcf8\ubb38\uc5d0 \uba85\uc2dc\ub41c \ub0b4\uc6a9\uc744 \uc815\ud655\ud788 \ubc18\uc601\ud558\ub294 \uc120\ud0dd\uc9c0\ub97c \uace0\ub974\uc2dc\uc624.",
        "3934c613-791b-4cab-869d-fafba77fa4c3": "- Q1(\uac1d\uad00\uc2dd): \ub2e4\uc74c \uc911 \uc774 \uc6d0\uace0\uc758 \ubc1c\ud589\uae30\uad00\uacfc \ubc1c\ud589\uc77c\uc744 \uc62c\ubc14\ub974\uac8c \ub9e4\uce6d\ud55c \uac83\uc740 \ubb34\uc5c7\uc778\uac00?",
        "943ce69e-dfb1-4089-bc1f-9be61a38174b": "A) \ubc1c\ud589\uae30\uad00: \uc815\ubcf4\ud1b5\uc2e0\uc0b0\uc5c5\uc9c4\ud765\uc6d0, \ubc1c\ud589\uc77c: 2024.03.08",
        "61b593cb-5a82-44c0-a896-092cce4a0cc1": "\uc9c8\ubb38 1",
        "be428685-4eea-4903-ab1a-4efc5c02c826": "\ub2e4\uc74c \ubb38\ub2e8\uc5d0 \uba85\uc2dc\ub41c \uad6d\uac00 \uc0ac\uc774\ubc84\ubcf4\uc548\uc744 \uac15\ud654\ud558\uae30 \uc704\ud55c \ud575\uc2ec \uc804\ub7b5 \uc694\uc18c\ub97c \ubaa8\ub450 \ub098\uc5f4\ud558\uace0, \uac01 \uc694\uc18c\uac00 \uc11c\ub85c \uc5b4\ub5bb\uac8c \ubcf4\uc644\ud558\ub294\uc9c0 \uac04\ub7b5\ud788 \uc124\uba85\ud558\uc2dc\uc624.",
        "c8991089-7218-4825-a107-9f46425f35c2": "\ubb38\uc11c\uc5d0 \uba85\uc2dc\ub41c \ud611\ub825 \uc8fc\uccb4\uc778 \uc0b0\uc5c5\uacc4, \uad6d\uc81c \ud30c\ud2b8\ub108, \ubc0f \uae30\ud0c0 \ube44 \uc5f0\ubc29\uae30\uad00\uacfc\uc758 \ud611\ub825\uc774 \ucd09\uc9c4\ud558\ub824\ub294 \ubc14\ub294 \ubb34\uc5c7\uc778\uac00?",
        "504c2007-3382-4934-bbf9-1149fe4919d3": "AI \uc5f0\uad6c \ubd84\uc57c\uc758 \uad6d\uc81c \ud611\ub825\uc5d0 \ub300\ud55c \uc6d0\uce59\uc801\uc774\uace0 \uc870\uc728\ub41c \uc811\uadfc \ubc29\uc2dd\uc758 \ud544\uc694\uc131\uc744 \uc124\uba85\ud558\uace0, \ud658\uacbd\uc801 \uc9c0\uc18d\uac00\ub2a5\uc131, \uc758\ub8cc, \uc81c\uc870 \ub4f1 \uae00\ub85c\ubc8c \uacfc\uc81c\ub97c \ud574\uacb0\ud558\uae30 \uc704\ud574 \uad6d\uc81c \ud611\ub825\uc744 \uc6b0\uc120\uc2dc\ud558\ub294 \uc774\uc720\ub97c \ub17c\ud558\uc2dc\uc624. \ub610\ud55c \uad6d\uc81c \uac00\uc774\ub4dc\ub77c\uc778 \ubc0f \ud45c\uc900\uc758 \uac1c\ubc1c\uacfc \uc774\ud589\uc744 \uc5b4\ub5bb\uac8c \uc9c0\uc6d0\ud574\uc57c \ud558\ub294\uc9c0 \uad6c\uccb4\uc801\uc73c\ub85c \uc11c\uc220\ud558\uc2dc\uc624.",
        "af36cebb-0fe4-4935-aa8f-c3d7a7b76632": "\ub2e4\uc9c0\uc120\ub2e4\ud615",
        "ae82e4ab-b3e7-412f-87e9-6c38bab01ba7": "MOVEit \ud30c\uc77c \uacf5\uc720 \uc18c\ud504\ud2b8\uc6e8\uc5b4\uc758 \ucde8\uc57d\uc810\uc744 \uc774\uc6a9\ud55c \ud574\ud0b9\uc5d0 \ub300\ud574 \ubbf8\uad6d \uc5f0\ubc29\uae30\uad00\uc774 \ubc1b\ub294 \uc601\ud5a5 \ud30c\uc545\uacfc \uc2dc\uc758\uc801\uc808\ud55c \uc870\uce58\ub97c \uc9c0\uc6d0\ud558\ub294 \uc8fc\uccb4\ub294 \ub204\uad6c\uc778\uac00?",
        "af66c07c-fd53-4704-a075-9e61aeb5ad12": "\uc9c8\ubb38 1",
        "4ab9ddc1-1f04-4fb4-8aa4-aab80fc6ed0c": "\ub2e4\uc74c \ubb38\ub2e8\uc5d0\uc11c AWS\uc640\uc758 \ud611\ub825\uc744 \ud1b5\ud574 \ub2ec\uc131\ud55c \ubaa9\ud45c\uc640 \uadf8\ub85c \uc778\ud55c \ud6a8\uacfc\ub97c \uc11c\uc220\ud558\uc2dc\uc624. \ud2b9\ud788 \uada4\ub3c4 \ub0b4 \ub370\uc774\ud130 \ucc98\ub9ac \ubc0f \ubd84\uc11d\uc758 \uc2e4\ud604, \uac00\uc7a5 \uc720\uc6a9\ud55c \uc774\ubbf8\uc9c0\ub9cc \ub2e4\uc6b4\ub9c1\ud06c\ud558\ub294 \ubc29\uc2dd\uc758 \uc758\ubbf8, \ub370\uc774\ud130 \uc804\uc1a1 \ub300\uc5ed\ud3ed\uc758 \uc808\uac10 \ubc0f \uc704\uc131 \uc6b4\uc601\uc758 \ud6a8\uc728\uc131 \ud5a5\uc0c1, \uc9c0\uad6c \ub3c4\ub2ec \uc804 \ubd88\ud544\uc694\ud55c \ub370\uc774\ud130\uc758 \ud544\ud130\ub9c1\uc774 \uac00\uc838\uc624\ub294 \uc2dc\uc0ac\uc810\uc744 \uc911\uc2ec\uc73c\ub85c \uc124\uba85\ud558\uc2dc\uc624.",
        "0ba1c99f-2b1c-427a-8317-e258aee9fba6": "\ub2e4\uc74c \uc911 \ubcf8\ubb38\uc5d0\uc11c \uc81c\uc2dc\ub41c AI \ud504\ub77c\uc774\ubc84\uc2dc \ubc0f \uc2dc\ubbfc\uad8c \uc9c0\uce68\uc758 \ubaa9\ud45c\uc5d0 \ud574\ub2f9\ud558\uc9c0 \uc54a\ub294 \uac83\uc740 \ubb34\uc5c7\uc785\ub2c8\uae4c?",
        "9740bcc2-b0cc-46ae-bdaa-a663aec63481": "A) \uc5f0\ubc29\uae09\uc5ec \ud504\ub85c\uadf8\ub7a8 \ubc0f \uc5f0\ubc29 \uacc4\uc57d\uc790\uc5d0 \ub300\ud574 AI\uac00 \ucc98\ubc8c\uc744 \uc720\ub3c4\ud558\uc9c0 \uc54a\ub3c4\ub85d \uba85\ud655\ud55c \uc9c0\uce68\uc744 \uc81c\uacf5",
        "1ef27f55-708d-417d-a4d3-33b43a0d57cc": "\ub2e4\uc74c \uc911 Walmart\uc758 DFW \uc9c0\uc5ed \ub4dc\ub860 \ubc30\uc1a1 \uc11c\ube44\uc2a4\uc5d0 \ub300\ud55c \uc124\uba85\uc73c\ub85c \uc633\uc740 \uac83\uc740 \ubb34\uc5c7\uc785\ub2c8\uae4c?",
        "304cc47d-15ea-4924-8842-464140f3fd93": "A) DFW \uc778\uad6c\uc758 60%\ub97c \ub300\uc0c1\uc73c\ub85c \ud558\uba70 \uc57d 15,000,000\uac00\uad6c\ub97c \uc11c\ube44\uc2a4\ud55c\ub2e4.",
        "d5c4fc6f-b08e-4d25-b3f1-4f0809e9b566": "\uc9c8\ubb38 1. 2022\u20132023\ub144 \ubc18\ub3c4\uccb4 \ubd84\uc57c\uc758 \uc815\uaddc\uc9c1 \ucc44\uc6a9\uc5d0 \uc9c0\uc6d0\ud55c \ud559\uc0dd \uc218\uac00 \uc99d\uac00\ud55c \ube44\uc728\uc740 \uc5bc\ub9c8\uc785\ub2c8\uae4c?",
        "222cf99c-408f-44db-9039-0215cf354c23": "\uc9c8\ubb38 2. 11\uc5b5 \ub2ec\ub7ec \uaddc\ubaa8\uc758 R&D \uc790\uae08\uc774 \ud22c\uc790\ud558\ub294 \uc138 \uac00\uc9c0 \uad6c\uccb4 \ud504\ub85c\uadf8\ub7a8\uc744 \ubaa8\ub450 \ub098\uc5f4\ud558\uc2dc\uc624: (1) \uacc4\uce21 \ud504\ub85c\uadf8\ub7a8 (2) \uad6d\ub9bd \uace0\uae09 \ud3ec\uc7a5 \uc81c\uc870 \ud504\ub85c\uadf8\ub7a8 (3) \ucd5c\ub300 3\uac1c\uc758 \uc2e0\uaddc Manufacturing USA \uc5f0\uad6c\uc18c.",
        "6996bede-e241-4c9e-a248-96e60ae138eb": "- Translate the term \"\ubbf8\uad6d\" into English as used in the document.",
        "68e6e800-d7c9-4d1e-b1c4-c348b0c17154": "- The document's context centers on which country?",
        "8aa2f8f0-9aed-4be3-b3b8-841f53465d6d": "\ubc31\uc545\uad00\uc758 AI \uc548\uc804 \uc11c\uc57d\uc5d0 \uba85\uc2dc\ub41c 3\uac00\uc9c0 \uc6d0\uce59\uc758 \uc774\ub984\uc744 \ub098\uc5f4\ud558\uace0, \uac01 \uc6d0\uce59\uc5d0 \ub300\ud574 \ud14d\uc2a4\ud2b8\uc5d0 \uc81c\uc2dc\ub41c \ud558\ub098\uc758 \uc138\ubd80 \uc870\ud56d\uc744 \uac04\ub7b5\ud788 \uc124\uba85\ud558\uc2dc\uc624.",
        "2a6ec816-9382-426f-b899-8167699d985a": "\uc704 \uc11c\uc57d\uc5d0\uc11c \uc81c\uc2dc\ub41c \uac01 \uc6d0\uce59\uc758 \ubaa9\ud45c\uac00 \uc11c\ub85c \uc5b4\ub5bb\uac8c \ubcf4\uc644\ub418\ub294\uc9c0 \ubd84\uc11d\ud558\uace0, \uae30\uc5c5\uc774 \uc2e4\uc81c\ub85c \ucde8\ud574\uc57c \ud560 \uad6c\uccb4\uc801 \uc870\uce58 \ub450 \uac00\uc9c0 \uc774\uc0c1\uc744 \uc0ac\ub840\uc640 \ud568\uaed8 \uc11c\uc220\ud558\uc2dc\uc624.",
        "625a9768-82f0-45ae-8d2a-16a0d7c89dd9": "Q1. \ub2e4\uc74c \ud30c\ud2b8\ub108\uc2ed\uc744 \uc2dd\ubcc4\ud558\uace0, \uac01 \ud30c\ud2b8\ub108\uc2ed\uc758 \ud575\uc2ec \ubaa9\ud45c\ub97c \uac04\ub2e8\ud788 \uc11c\uc220\ud558\uc2dc\uc624.",
        "31a37ef4-4fa2-4cbb-8bde-8d9b4f52986d": "- Google-Starlink: \uad6c\uae00 \ub370\uc774\ud130 \uc13c\ud130 \ub0b4 \uc9c0\uc0c1 \uc2a4\ud14c\uc774\uc158 \uc124\uce58\ub97c \ud1b5\ud574 \ubb34\uc5c7\uc744 \uc2e4\ud604\ud558\ub824 \ud558\ub294\uac00?",
        "dc89c197-0e6f-4aff-88a4-9dbd7b1dbb7f": "- Question 1: How many digits are in the decimal representation of the number 17?",
        "2c87ae69-72e9-4b3e-9dea-abbf6b30a0bd": "- Question 2: Is the number 17 odd or even? Provide a brief justification.",
        "888a71b0-79b7-4179-b29f-9569493e592f": "\ubbf8\uad6d\uc758 2023\ub144 3\uc6d4 \ubc1c\ud45c\ub41c \uad6d\uac00 \uc0ac\uc774\ubc84 \ubcf4\uc548 \uc804\ub7b5\uc758 5\ub300 \ud575\uc2ec \ubaa9\ud45c \uc911, \uc544\ub798 \ubcf4\uae30\uc5d0\uc11c \ud3ec\ud568\ub418\uc9c0 \uc54a\ub294 \ud56d\ubaa9\uc744 \uace0\ub974\uc2dc\uc624.",
        "b86a38b5-f35a-41eb-a318-04ca660ff320": "- A) \ud575\uc2ec \uae30\ubc18 \uc2dc\uc124 \ubc29\uc5b4",
        "79a2b5ce-0d23-4ff5-a36f-feabae961e14": "AI \uc548\uc804 \uc11c\uc57d\uc758 \ubc1c\ud45c \ubc30\uacbd\uacfc \ubaa9\uc801\uc744 \uac04\ub2e8\ud788 \uc124\uba85\ud558\uace0, \uc81c\uc2dc\ub41c 3\uac00\uc9c0 \uc6d0\uce59\uc774 \ubb34\uc5c7\uc778\uc9c0 \uc11c\uc220\ud558\uc2dc\uc624.",
        "872fdd77-1dde-401f-afc5-1ddae0129aae": "\ub2e4\uc74c \uc911 AI \uc548\uc804 \uc11c\uc57d\uc5d0 \ub3d9\uc758\ud55c \uc8fc\uc694 \uae30\uc5c5\uc5d0 \uc18d\ud558\uc9c0 \uc54a\ub294 \ud68c\uc0ac\ub97c \uace0\ub974\uc2dc\uc624.",
        "a3620ae1-833e-4e70-bf25-78b9ab1750e4": "Question 1:",
        "f0c04dc6-d67b-4854-aba1-20e7abb0b5bd": "From the \ucc38\uace0 \uc0ac\uc774\ud2b8 section, list three items that are US federal government domains (provide the domain names).",
        "5768d6b8-d7df-4aea-a07d-a8d032751d34": "Multiple Choice: Which real-time updates does the ERAdvisor app provide during pediatric emergency visits?",
        "a198bb63-2b2e-4e97-80cc-5a2cdfb4e2fa": "A) Wait times",
        "80caed2e-d888-498d-b048-6ebcdea14e8b": "\ub2e4\uc9c0\uc120\ub2e4\ud615: \ud788\ub85c\uc2dc\ub9c8 \ud68c\ub2f4\uc5d0\uc11c \ubbf8\uad6d-\uc77c\ubcf8 \uc591\uad6d \uc815\uc0c1\uc740 \uc8fc\ub85c \uc5b4\ub5a4 \ubd84\uc57c\uc758 \ud611\ub825 \uac15\ud654\ub97c \uac15\uc870\ud588\ub294\uac00?",
        "a41a2f3a-cf4b-4509-bc10-355e17b5d926": "A. \uc591\uc790\ucef4\ud4e8\ud305, \ubc18\ub3c4\uccb4, \uc778\uacf5\uc9c0\ub2a5",
        "8851aef7-577b-45a6-9caf-68af79034efc": "Q1. \ubcf8\ubb38\uc5d0 \ub098\ud0c0\ub09c \uae30\uc5c5\uc758 \uc57d\uc18d\uc744 4\uac00\uc9c0\ub85c \uc694\uc57d\ud558\uace0, \uac01 \uc57d\uc18d\uc774 AI\uc758 \uc0ac\ud68c\uc801 \uc704\ud5d8 \uac10\uc18c\uc640 \uac1c\uc778\uc815\ubcf4 \ubcf4\ud638\uc5d0 \uc5b4\ub5bb\uac8c \uae30\uc5ec\ud558\ub294\uc9c0 \uac04\ub2e8\ud788 \uc124\uba85\ud558\uc2dc\uc624.",
        "16e4da18-a1ef-4c9d-b63e-a43e87caeeb3": "Q2. \uc544\ub798 \ubcf4\uae30 \uc911 \ubb38\uc11c\uc758 \ucd9c\ucc98\ub85c \uba85\uc2dc\ub41c \uae30\uad00\uc740 \uc5b4\ub290 \uacf3\uc778\uac00? A) \ubbf8\uad6d \ubc31\uc545\uad00 B) \uad6d\uc81c \uc5f0\ud569 C) \uc138\uacc4\uc740\ud589 D) \uc720\ub7fd\uc5f0\ud569",
        "0560d030-b474-4217-a6e2-570f981a3ba1": "Q1. \ubcf8\ubb38\uc5d0 \uc81c\uc2dc\ub41c \ubd80\ubb38 \uc774\ub984\uc744 \ubaa8\ub450 \ub098\uc5f4\ud558\uc2dc\uc624.",
        "d7ef023b-d17d-40c9-ad69-f8659cecc21e": "Q2. \ub370\uc774\ud130\uc758 \ucd9c\ucc98\ub85c \uba85\uc2dc\ub41c \uad6d\uc81c\uae30\uad6c\ub97c \ubaa8\ub450 \uc5f4\uac70\ud558\uc2dc\uc624.",
        "640935c5-8846-475b-af92-569883e00447": "\uc9c8\ubb38 1",
        "5472d595-0a35-4717-9cfc-31c187ffec01": "2023\ub144 \uae00\ub85c\ubc8c \ud601\uc2e0\uc9c0\uc218 \ucd1d\uc810\uc5d0\uc11c \uc5b4\ub290 \ub098\ub77c\uac00 \ub354 \ub192\uc740 \uc810\uc218\ub97c \uae30\ub85d\ud558\uc600\ub098\uc694? \uc120\ud0dd\uc9c0 \uc911\uc5d0\uc11c \uc815\ub2f5\uc744 \uace0\ub974\uc2dc\uc624.",
        "afd04fbf-2661-468a-86dc-a9157f22f956": "\ud56d\ubaa9 \u2463\uc5d0 \ub530\ub77c: AI \uc2dc\uc2a4\ud15c\uc758 \uc548\uc804\uacfc \ubcf4\uc548 \ud655\ubcf4\ub97c \uc704\ud55c \uc2e0\ub8b0\ud560 \uc218 \uc788\uace0 \uc548\uc804\ud55c AI \uc2dc\uc2a4\ud15c \uc124\uacc4 \uc6d0\uce59\uacfc \uc704\ud5d8 \uad00\ub9ac \uc804\ub7b5\uc744 \uc81c\uc2dc\ud558\uace0, \uc774\ub97c \uc2e4\uc81c \uc2dc\uc2a4\ud15c\uc5d0 \uc801\uc6a9\ud560 \ub54c\uc758 \uc8fc\uc694 \uc694\uc18c\uc640 \ub3c4\uc804 \uacfc\uc81c\ub97c \uc11c\uc220\ud558\uc2dc\uc624.",
        "c6185dd3-2168-440f-954d-4410e2ecfca2": "\ud56d\ubaa9 \u2464\uc5d0 \ub530\ub77c: AI \ud559\uc2b5 \ubc0f \ud14c\uc2a4\ud2b8\ub97c \uc704\ud55c \uacf5\uc720 \uacf5\uac1c \ub370\uc774\ud130\uc640 \uc81c\ubc18 \ud658\uacbd \uad6c\ucd95\uc758 \uad6c\uc131 \uc694\uc18c\ub97c \uc81c\uc2dc\ud558\uace0, \ub370\uc774\ud130 \ud488\uc9c8 \uad00\ub9ac\uc640 \uc811\uadfc\uc131 \ud655\ub300, \ud14c\uc2a4\ud2b8/\uad50\uc721 \uc790\uc6d0\uc758 \ud655\ubcf4\ub97c \ub2ec\uc131\ud558\uae30 \uc704\ud55c \uc2e4\ud589 \uacc4\ud68d\uacfc \uae30\ub300 \ud6a8\uacfc, \uadf8\ub9ac\uace0 \uc7a0\uc7ac\uc801 \ubb38\uc81c\uc810\uc744 \ubd84\uc11d\ud558\uc2dc\uc624.",
        "41ef2030-7cc9-49d2-9e5f-bc6a3eb00f5c": "Short answer: What specific FAA regulatory change is described, and what exemption does it grant to companies like Wing for drone operations?",
        "4f4bad74-5e8f-4fbd-888e-89bb57124138": "Essay/Discussion: Based on the provided context, discuss how FAA regulatory relaxation and advances in drone delivery technology may enable widespread drone deliveries across the United States. Include examples from the text, such as pilot operations in multiple cities and competition with Zipline, and explain the potential environmental and efficiency benefits.",
        "60100f3e-670f-48df-b6d4-3826aa939b8f": "Question 1 (Short answer):",
        "ddbd8d90-8b2f-47fc-b664-55791a86b4b8": "\ub2e4\uc74c \ubc1c\ucdcc\uc5d0 \ub530\ub77c, \uad6d\uac00 AI R&D \uc804\ub7b5 \uacc4\ud68d\uc758 \uc804\ub7b5 \u2460\uacfc \uc804\ub7b5 \u2461\uc758 \ud575\uc2ec \ub0b4\uc6a9\uacfc \ubaa9\ud45c\ub97c \uac01\uac01 \uc11c\uc220\ud558\uc2dc\uc624. \ud2b9\ud788 \uc804\ub7b5 \u2460\uc740 \uc5b4\ub5a4 \uc911\uc810\uacfc \uae30\ub300 \ud6a8\uacfc\ub97c \ub9d0\ud558\uace0, \uc804\ub7b5 \u2461\ub294 \uc778\uac04-AI \ud611\uc5c5\uc758 \ubc1c\uc804\uc744 \uc704\ud55c \uad6c\uccb4\uc801 \ubc29\ud5a5\uc131\uc5d0 \ub300\ud574 \ubb34\uc5c7\uc744 \uc81c\uc2dc\ud558\ub294\uac00?",
        "5d8cbf07-938b-4a36-a17d-1e8a0069ab80": "\uc11c\uc220\ud615 \uc9c8\ubb38: \uc591\uc790 AI \uac70\ubc84\ub10c\uc2a4 \uc6cc\ud0b9\uadf8\ub8f9\uc758 \uc124\ub9bd \ubaa9\uc801\uacfc NSF- AISG\uc758 \uacf5\ub3d9 \uc5f0\uad6c \ubc0f \uad50\uc721 \uc790\uae08 \uc9c0\uc6d0\uc758 \ud575\uc2ec \ub0b4\uc6a9\uc744 \uc694\uc57d\ud558\uace0, \uc774 \ub450 \uc774\ub2c8\uc154\ud2f0\ube0c\uac00 \uc81c\uc2dc\ud558\ub294 \u201c\uc548\uc804\ud558\uace0 \ucc45\uc784 \uc788\ub294 AI \uacf5\uc720 \uc6d0\uce59\u201d \ubc0f \uc0c1\ud638 \uae30\uc220 \ubc1c\uc804\uacfc \uc548\uc804\uc5d0 \ub300\ud55c \ud5cc\uc2e0\uc774 \uc5f0\uad6c \ubc0f \uad50\uc721 \uc790\uae08 \uc9c0\uc6d0\uc5d0 \uc5b4\ub5a4 \ud568\uc758\ub97c \uac16\ub294\uc9c0 \ub17c\ud558\uc2dc\uc624.",
        "07577b1e-df15-4509-84d3-47bbd3da0984": "\uac1d\uad00\uc2dd \uc9c8\ubb38: \uc81c9\ucc28 EU-\ubbf8\uad6d \uc0ac\uc774\ubc84 \ub300\ud654\uc5d0\uc11c \uac15\ud654\ub41c \ud611\ub825\uc758 \ud575\uc2ec \ud3ec\uc778\ud2b8\ub85c \uc633\uc740 \uac83\uc740 \ubb34\uc5c7\uc778\uac00?",
        "ff01a229-b58c-41a1-a881-adcb62ed3245": "- Question 1 (\uc11c\uc220\ud615): \uc774 \ud30c\ud2b8\ub108\uc2ed\uc758 \ud575\uc2ec \ubaa9\ud45c\uc640 \uc704\uc131\uc5d0\uc11c AI \ubaa8\ub378\uc744 \uc6d0\ud074\ub9ad\uc73c\ub85c \ubc30\ud3ec\ud558\ub294 \ubc29\uc2dd\uc774 \uc9c0\uc0c1 \uc2dc\uc2a4\ud15c \uc758\uc874\ub3c4 \ubc0f \ud1b5\uc2e0 \uc778\ud504\ub77c \ube44\uc6a9\uc5d0 \ubbf8\uce58\ub294 \uae30\ub300 \ud6a8\uacfc\ub97c \uc124\uba85\ud558\uc2dc\uc624.",
        "930130f3-0040-4cc9-b559-8809f2d22308": "- Question 2 (\uac1d\uad00\uc2dd): IBM\uc774 American Tower\uc640\uc758 \ud611\ub825\uc744 \ud1b5\ud574 \ub2ec\uc131\ud558\ub824\ub294 \uc8fc\uc694 \ubaa9\uc801\uc740 \ubb34\uc5c7\uc778\uac00?",
        "69ddf7bb-f997-4848-9a7f-e6b664f78df0": "\ub2e4\uc74c \ud45c\uc5d0 \ub098\ud0c0\ub09c \ubbf8\uad6d \uc8fc\uc694 ICT \uae30\uc5c5 \uc911 \uc2dc\uac00\ucd1d\uc561\uc774 \uac00\uc7a5 \ud070 \ud68c\uc0ac\ub294 \uc5b4\ub290 \uac83\uc778\uac00?",
        "1743f680-e71b-4ce3-b123-482370e1f937": "A. Microsoft  B. Apple  C. NVIDIA  D. Alphabet",
        "a4e977fa-70b1-40a9-821e-17ee62a3c88d": "Pillar 1\uc5d0 \uad00\ud55c \ub2e8\ub2f5\ud615 \uc9c8\ubb38",
        "d7433a88-1bc8-47a0-b35e-af40081c75cc": "\uad6d\uac00 \uc2a4\ud399\ud2b8\ub7fc \uc804\ub7b5\uc758 Pillar 1\uacfc \uadf8 \ud558\uc704 \ubaa9\ud45c 1.1, 1.2, 1.3\uc758 \ub0b4\uc6a9\uc740 \ubb34\uc5c7\uc774\uba70, \uac01 \ud558\uc704 \ubaa9\ud45c\uac00 \ubbf8\uad6d\uc758 \ucca8\ub2e8 \ubc0f \uc2e0\ud765 \uae30\uc220 \ubd84\uc57c\uc5d0\uc11c \ub9ac\ub354\uc2ed \ud655\ubcf4\uc5d0 \uc5b4\ub5bb\uac8c \uae30\uc5ec\ud558\ub294\uc9c0 \uac04\ub7b5\ud788 \uc124\uba85\ud558\uc2dc\uc624.",
        "1e0ae716-0056-4a43-a773-5be84aaf41f8": "- Question 1 (Multiple choice): In the document's table of contents, which section number corresponds to ICT \uc8fc\uc694 \ubc95\ub839 \ubc0f \uaddc\uc81c?",
        "4077694f-07cc-4614-8e18-849264fc9a9a": "A) 1",
        "732470f1-e43e-497d-b3b5-0af1ebce6916": "\uac1d\uad00\uc2dd: \ub2e4\uc74c \uc0b0\uc5c5 \uc911 AI \ucc57\ubd07\uc758 \ub354 \uc815\ud655\ud558\uace0 \ud6a8\uc728\uc801\uc778 \uc194\ub8e8\uc158\uc73c\ub85c \ud61c\ud0dd\uc744 \ubc1b\uc744 \uac83\uc73c\ub85c \uc5b8\uae09\ub41c \uc0b0\uc5c5\uc740 \uc5b4\ub290 \uac83\ub4e4\uc778\uac00?",
        "8368dd01-f73a-47c5-9ba1-f309cd3fea1d": "- a) \uace0\uac1d \uc11c\ube44\uc2a4",
        "fe7bd2f7-f705-425c-8213-da97bcaba817": "\uac1d\uad00\uc2dd",
        "13768bd7-972a-4b28-bcac-573fd3ee0d43": "\ub2e4\uc74c \uc911 \ubcf8\ubb38\uc5d0 \ub530\ub77c \ub514\uc9c0\ud138 \ud2b8\uc708\uc774 \uad70\uc0ac \uc791\uc804\uc744 \uacc4\ud68d\ud558\uace0 \uc2e4\ud589\ud558\ub294 \ub370 \uae30\ub300\ub418\ub294 \uc5ed\ud560\uc740 \ubb34\uc5c7\uc778\uac00?",
        "7c9faa9d-9c94-43f1-bfe9-67d8a302764b": "Question 1 (Multiple Choice):",
        "863904bf-4b3b-4ee4-a5eb-9ed981331424": "Which of the following is described as part of the Department of Commerce's plan to create a job and talent pipeline for the semiconductor industry?",
        "945312a0-128f-45ce-9d95-1fd94c2fba42": "\ub2e4\uc74c \ub450 \ubb38\uc81c\ub97c \uc81c\ucd9c\ud558\uc2ed\uc2dc\uc624.",
        "45d40276-9d8e-4e28-84b3-4e9f5bc55ed9": "NTIA\uc758 \uc815\uc2dd \uba85\uce6d\uacfc \uc18c\uc18d \uae30\uad00\uc740 \ubb34\uc5c7\uc774\uba70, \uc774 \uae30\uad00\uc758 \uc8fc\uc694 \uc5ed\ud560\uc740 \ubb34\uc5c7\uc778\uac00? \ud2b9\ud788 \ub300\ud1b5\ub839\uc5d0\uac8c \uc790\ubb38\uc744 \uc81c\uacf5\ud558\ub294 \ucc45\uc784\uc5d0 \ub300\ud574 \uc11c\uc220\ud558\uc2dc\uc624.",
        "56407032-e0dd-4255-8427-8d35fbdb469d": "\ub2e4\uc9c0\uc120\ub2e4\ud615: \ubbf8\uad6d\uc758 \ud1b5\ud569 \uae00\ub85c\ubc8c 6G \ud45c\uc900 \uac1c\ubc1c\uc5d0 \uc801\uadf9\uc801\uc73c\ub85c \ub178\ub825\ud558\ub294 \uc870\uc9c1\uc740 \ubb34\uc5c7\uc778\uac00?",
        "05f254df-3de3-41bd-8756-0af0d86cfb40": "- A) IEEE",
        "b87644ce-8ab8-4843-88db-f2ee89729359": "Zipline\uc740 \uc5b4\ub5a4 \uc9c0\uc5ed\uc5d0\uc11c \uc774\ubbf8 \uc131\uacf5\uc801\uc778 \ubc30\uc1a1\uc744 \uc218\ud589\ud574 \uc654\uc73c\uba70, \ubbf8\uad6d \ub0b4 \ud655\uc7a5\uc744 \uc5b4\ub5a4 \ubc29\ud5a5\uc73c\ub85c \uacc4\ud68d\ud558\uace0 \uc788\ub294\uac00? (\uac04\ub2e8\ud788 \uc11c\uc220)",
        "36d941fb-3f63-467c-8613-9694a843a6fe": "Wing\uc758 \uc790\ub3d9\ud654\ub41c \ub4dc\ub860 \ubc30\uc1a1 \ub124\ud2b8\uc6cc\ud06c\ub294 \ub4dc\ub860\uc744 \uc5b4\ub5bb\uac8c \ubc30\uce58\ud558\ub294\uc9c0 \uc124\uba85\ud558\uace0, \ubbf8\uad6d \ub0b4 \ud655\uc7a5\uc758 \uc8fc\uc694 \ubaa9\ud45c\uc778 \ubc30\uc1a1 \uc2dc\uac04 \ub2e8\ucd95\uacfc \ud658\uacbd \uc601\ud5a5 \uac10\uc18c\ub97c \ud3ec\ud568\ud558\uc5ec \uc694\uc57d\ud558\uc2dc\uc624.",
        "4261d372-a7b2-4eb8-8b03-eb080b63a27c": "Approximately how much is the initial NSTC investment, and what core role is NSTC expected to play in the nation\u2019s semiconductor R&D efforts?",
        "460a861d-bf27-484d-97f7-aeeebc6b0a32": "Name the two CHIPS Act R&D programs mentioned and explain how they are designed to address core aspects of semiconductor manufacturing\u2014from advanced packaging to digital twin technology\u2014and why this supports a broader strategy for maintaining U.S. leadership in the industry.",
        "8a658469-f774-4c9f-adff-6bef5d7e211d": "\ubb38\uc81c 1 (\uc11c\uc220\ud615)",
        "f61af39c-17ab-455a-afa8-60cd4ce8be85": "\ubb38\uc11c\uc758 3\uc7a5\uc5d0 \ud574\ub2f9\ud558\ub294 '\uae30\uc220 \uac1c\ubc1c\uc744 \ud1b5\ud55c \uc804\ub840 \uc5c6\ub294 \uc2a4\ud399\ud2b8\ub7fc \ud601\uc2e0, \uc811\uadfc \ubc0f \uad00\ub9ac' \ubd80\ubd84\uc758 \uc138\ubd80 \ud56d\ubaa9 3.1, 3.2, 3.3\ub97c \uac01\uac01 \uac04\ub7b5\ud788 \uc694\uc57d\ud558\uace0, \uc774 \uc138 \uac00\uc9c0\uac00 \uc2a4\ud399\ud2b8\ub7fc \uc815\ucc45\uc758 \uacf5\ud1b5 \ubaa9\ud45c\uc778 \ud601\uc2e0\uc801 \ud65c\uc6a9 \ud655\ub300, \ucd1d\uccb4\uc801 \uc774\ud574 \uc99d\uc9c4, \uc811\uadfc\uc131 \ud655\ub300\uc5d0 \uc5b4\ub5bb\uac8c \uae30\uc5ec\ud558\ub294\uc9c0 \uc124\uba85\ud558\uc2dc\uc624."
    },
    "corpus": {
        "69db4a2f-46a3-4db6-9a36-fc2f506a41ce": "4",
        "553dcf19-20a0-4f5a-ae65-b5a67f7dfbc1": "\uc678\uacfd \uc9c0\uc5ed \ub4f1\uc5d0 \ud65c\uc6a9\ud560 \uc218 \uc788\ub3c4\ub85d \ubb34\uc120 \ud5c8\uac00\uc790\ub4e4\uc5d0\uac8c \uc778\uc13c\ud2f0\ube0c \uc81c\uacf5\n\uc8fc\uc694\uc0b0\ud558 \uc870\uc9c1\n\ucd9c\ucc98 : \ubbf8\uad6d \uc5f0\ubc29\ud1b5\uc2e0\uc704\uc6d0\ud68c",
        "e46dbc1b-fbeb-48bd-9d7d-491cad4d6402": "\ubcf4\uc548, \uc2e0\ub8b0\uc131\uc744 \ud655\uc778\ud558\ub294 \ub370 \ub3c4\uc6c0\uc774 \ub418\ub294 \ud45c\uc900, \ub3c4\uad6c, \ud14c\uc2a4\ud2b8 \uac1c\ubc1c\u2023 \uc0dd\ubb3c\ud559\uc801 \ud569\uc131 \uc2a4\ud06c\ub9ac\ub2dd\uc5d0 \ub300\ud55c \uac15\ub825\ud55c \uae30\uc900 \uac1c\ubc1c\u2023 AI\uac00 \uc0dd\uc131\ud55c \ucf58\ud150\uce20\ub97c \ud0d0\uc9c0\ud558\uace0 \uacf5\uc2dd \ucf58\ud150\uce20\ub97c \uc778\uc99d\ud558\uae30 \uc704\ud55c \ud45c\uc900\uacfc \ubaa8\ubc94\uc0ac\ub840\ub97c \ud655\ub9bd\ud558\uc5ec, AI\ub97c \uc774\uc6a9\ud55c \uc0ac\uae30 \ubc0f \uc18d\uc784\uc218\ub85c\ubd80\ud130 \uad6d\ubbfc\uc744 \ubcf4\ud638\u2023 \uc911\uc694\ud55c \uc18c\ud504\ud2b8\uc6e8\uc5b4\uc758 \ucde8\uc57d\uc810\uc744 \ucc3e\uc544 \uc218\uc815\ud560 \uc218 \uc788\ub294 AI \ud234 \uac1c\ubc1c\uc744 \uc704\ud55c \ud504\ub85c\uadf8\ub7a8 \uc218\ub9bd\u2023 AI\uc640 \ubcf4\uc548\uc5d0 \ub300\ud55c \ucd94\uac00 \uc870\uce58\ub97c \uc9c0\uc2dc\ud558\ub294 \uad6d\uac00\uc548\ubcf4\uac01\uc11c \uac1c\ubc1c\n\ubbf8\uad6d\uc778\uc758 \uac1c\uc778\uc815\ubcf4 \ubcf4\ud638\u2023 \uac1c\uc778\uc815\ubcf4\ubcf4\ud638 \uae30\uc220\uc758 \uac1c\ubc1c\uacfc \ud65c\uc6a9\uc744 \uac00\uc18d\ud654 \ud558\uae30 \uc704\ud55c \uc5f0\ubc29\uc815\ubd80\uc758 \uc9c0\uc6d0\uc744 \uc6b0\uc120\uc2dc\u2023 \uc554\ud638\ud654 \ub3c4\uad6c \ub4f1 \uac1c\uc778\uc815\ubcf4\ubcf4\ud638 \uc5f0\uad6c \ubc0f \uae30\uc220 \uac15\ud654\u2023 \uae30\uad00\uc774 \uc0c1\uc5c5\uc801 \uc6a9\ub3c4\uc758 \uc815\ubcf4 \uc218\uc9d1 \ubc0f \uc774\uc6a9\ubc29\ubc95 \ud3c9\uac00, AI\uc704\ud5d8 \uace0\ub824 \uc81c\uace0 \uc704\ud55c \uac1c\uc778\uc815\ubcf4 \uc9c0\uce68 \uac15\ud654\u2023 \uc5f0\ubc29\uae30\uad00\uc774 \uac1c\uc778\uc815\ubcf4\ubcf4\ud638 \uae30\uc220\uc758 \ud6a8\uacfc\ub97c \ud3c9\uac00\ud560 \uc218 \uc788\ub294 \uc9c0\uce68 \uac1c\ubc1c\ud615\ud3c9\uc131 \ubc0f \uc2dc\ubbfc\uad8c \uc99d\uc9c4\u2023 AI \uc54c\uace0\ub9ac\uc998\uc774 \ucc98\ubc8c\uc744 \uc720\ub3c4\ud558\uc9c0 \uc54a\ub3c4\ub85d \uc5f0\ubc29\uae09\uc5ec \ud504\ub85c\uadf8\ub7a8,",
        "987a5ce8-467f-4096-97b6-d50d0beed5b9": "AI \uad00\ub828 \uc758\ub8cc \ubd84\uc57c \uc704\ud5d8 \ubcf4\uace0 \uccb4\uacc4 \uc218\ub9bd\u2023 AI \uc9c0\uc6d0 \uad50\uc721 \ub3c4\uad6c \ubc30\ud3ec \uc9c0\uc6d0\n\uadfc\ub85c\uc790 \uc9c0\uc6d0\u2023 \uc77c\uc790\ub9ac \ub300\uccb4, \ub178\ub3d9 \uae30\uc900, \uc9c1\uc7a5 \ub0b4 \ud615\ud3c9\uc131, \uac74\uac15, \uc548\uc804, \ub370\uc774\ud130 \uc218\uc9d1 \ubb38\uc81c\ub97c \ud574\uacb0\ud568\uc73c\ub85c\uc368 \uadfc\ub85c\uc790\uc5d0\uac8c AI\uc758 \ud53c\ud574\ub97c \uc644\ud654\ud558\uace0 \uc774\uc810\uc744 \uadf9\ub300\ud654\ud558\uae30 \uc704\ud55c \uc6d0\uce59\uacfc \ubaa8\ubc94\uc0ac\ub840 \uac1c\ubc1c\u2023 AI\uc758 \ub178\ub3d9\uc2dc\uc7a5\uc5d0 \ub300\ud55c \uc7a0\uc7ac\uc801 \uc601\ud5a5\ub825 \ubcf4\uace0\uc11c \uc791\uc131, AI\ub85c \uc778\ud574 \ub178\ub3d9 \uc911\ub2e8\uc5d0 \uc9c1\uba74\ud55c \uadfc\ub85c\uc790\uc5d0 \ub300\ud55c \uc5f0\ubc29 \uc9c0\uc6d0 \uac15\ud654 \ubc29\uc548 \uc5f0\uad6c\ud601\uc2e0 \ubc0f \uacbd\uc7c1 \ucd09\uc9c4\u2023 \uad6d\uac00\uc778\uacf5\uc9c0\ub2a5\uc5f0\uad6c\uc9c0\uc6d0 \ud30c\uc77c\ub7ff, \uc758\ub8cc \ubc0f \uae30\ud6c4 \ubcc0\ud654 \ub4f1 \uc911\uc694 \ubd84\uc57c\uc758 AI \uc5f0\uad6c \ubcf4\uc870\uae08 \ud655\ub300\u2023 \uae30\uc5c5\uc758 AI \ud601\uc2e0\uc744 \uc9c0\uc6d0\ud558\ub294 \uacf5\uc815\ud558\uace0 \uac1c\ubc29\uc801\uc774\uba70 \uacbd\uc7c1\ub825 \uc788\ub294 AI \uc0dd\ud0dc\uacc4 \uc870\uc131\u2023 \ube44\uc790 \uae30\uc900, \uc778\ud130\ubdf0, \uc2ec\uc0ac\ub97c \uac04\uc18c\ud654\ud558\uc5ec \uc219\ub828\ub41c \uc774\ubbfc\uc790\uc640 \ud575\uc2ec \ubd84\uc57c\uc758 \uc804\ubb38\uc9c0\uc2dd\uc744 \uac00\uc9c4 \ube44\uc774\ubbfc\uc790\uc758 \ubbf8\uad6d \ub0b4 \uccb4\ub958\uc640 \uc77c\ud560 \uae30\ud68c \ud655\ub300\ubbf8\uad6d\uc758 \ub9ac\ub354\uc2ed \uac15\ud654\u2023 \uc548\uc804\ud558\uace0 \uc2e0\ub8b0\ud560 \uc218 \uc788\ub294 AI \ud65c\uc6a9\uc744 \uc704\ud55c \uc774\ud574\uad00\uacc4\uc790\uc758 \ucc38\uc5ec \ud655\ub300,",
        "3a53f459-81b5-419f-90de-169710644f19": "\uc774 \uc790\uae08\uc740 \ucc28\uc138\ub300 \ubc18\ub3c4\uccb4\ub97c \uc0dd\uc0b0\ud560 \uc218 \uc788\ub294 \ucd5c\ucca8\ub2e8 \uacf5\uc7a5 \uac1c\ubc1c\uc744 \uac00\uc18d\ud654\ud560 \ubaa9\uc801\uc774\uc790, \uad6d\uac00 \ubc18\ub3c4\uccb4 \uc778\ud504\ub77c \uc7ac\uac74\uc5d0 \ub300\ud55c \uc815\ubd80\uc758 \uacb0\ub2e8\uc744 \ubcf4\uc5ec\uc90c. \uc778\ud154(Intel), \uae00\ub85c\ubc8c\ud30c\uc6b4\ub4dc\ub9ac\uc2a4 (GlobalFoundries), TSMC\uc640 \uac19\uc740 \uae30\uc5c5\ub4e4\uc774 \uc7a0\uc7ac\uc801 \uc218\ud61c\uc790\ub85c, \uc218\ucc9c \uac1c\uc758 \uc77c\uc790\ub9ac \ucc3d\ucd9c\uacfc \ubbf8\uad6d\uc758 \uc81c\uc870 \ub2a5\ub825 \uac15\ud654\ub97c \uc57d\uc18d\ud558\ub294 \ud504\ub85c\uc81d\ud2b8\ub97c \uc9c4\ud589 \uc911\uc784\u2022 \uc790\uae08\uc758 \uc2e0\uc18d\ud55c \ubc30\uce58\ub97c \uc704\ud574, \ubbf8\uad6d \uc0c1\ubb34\ubd80\ub294 2024\ub144 3\uc6d4 \ub9d0\uae4c\uc9c0 \uc8fc\uc694 \ubcf4\uc870\uae08\uc744 \ubc30\ubd84\ud560 \uacc4\ud68d\uc744 \ubc1c\ud45c\ud568. \ud504\ub85c\uc81d\ud2b8 \ube44\uc6a9\uc758 \ucd5c\ub300 15%\ub97c \uc9c0\uc6d0\ud558\ub294 \ubcf4\uc870\uae08\uc740 \ubc18\ub3c4\uccb4 \uc0b0\uc5c5\uc5d0 \ub300\ud55c \ubbfc\uac04 \ubd80\ubb38\uc758 2,300\uc5b5 \ub2ec\ub7ec(\uc57d 286\uc870 2,000\uc5b5 \uc6d0) \uc774\uc0c1\uc758 \ud22c\uc790\ub97c \ucd09\uc9c4\ud560 \uac83\uc73c\ub85c \uae30\ub300\ub418\uba70, \uc774\ub294 \uac15\ub825\ud55c \ubbfc\uad00 \ud30c\ud2b8\ub108\uc2ed\uc758 \uc2e4\ud604\uc744 \ubcf4\uc5ec\uc90c\n \uad6d\uac00 \ubc18\ub3c4\uccb4 \uae30\uc220 \uc13c\ud130 \uc124\ub9bd \ubc0f \uc5f0\uad6c\uac1c\ubc1c \ud22c\uc790\u2022 \uad6d\uac00 \ubc18\ub3c4\uccb4 \uae30\uc220 \uc13c\ud130(NSTC)\uc758 \uc124\ub9bd\uc740 \ubbf8\uad6d\uc774 \ubc18\ub3c4\uccb4 \ud601\uc2e0 \ubd84\uc57c\uc5d0\uc11c \ub9ac\ub354\uc2ed\uc744 \uc720\uc9c0\ud558\ub824\ub294 \ub178\ub825\uc758 \uc911\uc694\ud55c \uc774\uc815\ud45c\uc784.",
        "f1e31416-85f0-498c-a531-948bba709eda": "27 \n\u2161. ICT \uc774\uc288 Top10 \u2469\ubbf8 \uad6d\ubc29\ubd80, \ub514\uc9c0\ud138 \ud2b8\uc708 \uae30\uc220 \ub3c4\uc785 \ud655\ub300\n \uad6d\ubc29\ubd80\uc758 \ub514\uc9c0\ud138 \ud2b8\uc708 \uae30\uc220 \ud65c\uc6a9 \ud604\ud669\u2022 \ub514\uc9c0\ud138 \ud2b8\uc708\uc774 \uc804\ud22c \uc218\ud589\uc5d0\uc11c\uc758 \ubcc0\ud601\uc801 \uc7a0\uc7ac\ub825\uc744 \uc778\uc815\ubc1b\uace0 \uc788\uc74c. \uc9c0\uba58\uc2a4 \uc815\ubd80 \uae30\uc220 (Siemens Government Technologies)\uc758 \uc874 \uc6b0\uc2a4\ud2f0\uce74(John Ustica) \uc0ac\uc7a5\uc740 \uad11\ubc94\uc704\ud55c \ub370\uc774\ud130 \uc785\ub825\uc744 \ud65c\uc6a9\ud558\uc5ec \uacb0\uacfc\ub97c \ubaa8\ub378\ub9c1\ud558\uace0 \uc608\uce21\ud558\ub294 \uae30\uc220\uc758 \ub2a5\ub825\uc744 \uac15\uc870\ud568. \uc774\ub7ec\ud55c \uc778\uc2dd\uc740 \uacf5\uae09\ub9dd \uad00\ub9ac \ubc0f \uc804\uc7a5 \ub2a5\ub825 \ud5a5\uc0c1 \ub4f1\uc758 \uc791\uc5c5\uc5d0\uc11c \ub514\uc9c0\ud138 \ud2b8\uc708\uc758 \uac1c\ubc1c \ubc0f \uc801\uc6a9\uc744 \uac00\uc18d\ud654\ud558\uae30 \uc704\ud55c \ub2e4\uc591\ud55c DOD \uc870\uc9c1\uc758 \ud504\ub85c\uc81d\ud2b8\ub85c \uc774\uc5b4\uc9d0\u2022 \uacf5\uad70\uc740 \ub514\uc9c0\ud138 \ud2b8\uc708 \uae30\uc220 \ucc44\ud0dd\uc5d0 \uc788\uc5b4 \uc120\ub450\uc8fc\uc790\ub85c, \uc704\uce58\ud0c0 \uc8fc\ub9bd\ub300\ud559\uad50 \uad6d\ub9bd \ud56d\uacf5 \uc5f0\uad6c\uc18c\uc5d0 1\uc5b5 \ub2ec\ub7ec(\uc57d 1,240\uc5b5 \uc6d0) \uacc4\uc57d\uc744 \uc218\uc5ec\ud568\uc73c\ub85c\uc368 \uc785\uc99d\ub428.",
        "b3c95e12-70c8-4038-a738-9575670c520e": "\u00b7 \ubc1c\ud589\u2024\ud3b8\uc9d1 : \uc815\ubcf4\ud1b5\uc2e0\uc0b0\uc5c5\uc9c4\ud765\uc6d0\u00b7 \ubc1c\ud589\uc77c\uc790 : 2024.03.08\ud574\ub2f9 \uc6d0\uace0\uc5d0 \ub300\ud574 \uc0ac\uc804 \ub3d9\uc758 \uc5c6\uc774 \uc0c1\uc5c5 \uc0c1 \ub610\ub294 \ub2e4\ub978 \ubaa9\uc801\uc73c\ub85c\ubb34\ub2e8 \uc804\uc7ac\u00b7\ubcc0\uacbd\u00b7\uc81c 3\uc790 \ubc30\ud3ec \ub4f1\uc744 \uae08\ud569\ub2c8\ub2e4.\ub610\ud55c \ubcf8 \uc6d0\uace0\ub97c \uc778\uc6a9\ud558\uc2dc\uac70\ub098 \ud65c\uc6a9\ud558\uc2e4 \uacbd\uc6b0\u25b3\ucd9c\ucc98 \ud45c\uae30 \u25b3\uc6d0\ubcf8 \ubcc0\uacbd \ubd88\uac00 \ub4f1\uc758 \uc774\uc6a9 \uaddc\uce59\uc744 \uc9c0\ud0a4\uc154\uc57c \ud569\ub2c8\ub2e4. Copyright 2024 NIPA \uc815\ubcf4\ud1b5\uc2e0\uc0b0\uc5c5\uc9c4\ud765\uc6d0 All Rights Reserved. Printed in Korea",
        "6994870b-693b-47f5-aaf4-99a0ee0fceb8": "\uc5ec\uae30\uc5d0\ub294 \ud575\uc2ec \uae30\ubc18 \uc2dc\uc124 \ubc29\uc5b4, \uc704\ud611 \ud589\uc704\uc790 \uad50\ub780, \ubcf4\uc548 \ubc0f \ud68c\ubcf5\ub825\uc744 \ucd09\uc9c4\ud558\uae30 \uc704\ud55c \uc2dc\uc7a5 \uc138\ub825 \ud615\uc131, \ud68c\ubcf5\ub825 \uc788\ub294 \ubbf8\ub798\uc5d0 \ub300\ud55c \ud22c\uc790, \uad6d\uc81c \ud30c\ud2b8\ub108\uc2ed \uad6c\ucd95\uc774 \ud3ec\ud568\ub428. \ucc45\uc784 \uc18c\uc7ac\ub97c \ub300\uaddc\ubaa8 \uc870\uc9c1\uc73c\ub85c \uc7ac\uc870\uc815\ud558\uace0 \uac15\ub825\ud55c \ud611\uc5c5\uacfc \ubcf4\uc548 \uae30\uc220, \uc778\ub825 \uac1c\ubc1c\uc5d0 \ub300\ud55c \uc7a5\uae30 \ud22c\uc790\ub85c \uad6d\uac00 \uc0ac\uc774\ubc84\ubcf4\uc548\uc744 \uac15\ud654\ud558\ub824\ub294 \ud589\uc815\ubd80\uc758 \uc758\uc9c0\ub97c \ub0b4\ud3ec\ud568\n \ube45\ud14c\ud06c \uae30\uc5c5, \ud074\ub77c\uc6b0\ub4dc \ubcf4\uc548 \uac15\ud654 \uc870\uce58\u2022 \ucd5c\uadfc \ubbf8\uad6d \uc815\ubd80 \uad00\ub9ac\ub4e4\uc758 \uc774\uba54\uc77c\uc774 \ud574\ud0b9\ub41c \uc0ac\uac74\uc5d0 \ub300\uc751\ud558\uc5ec, \uc544\ub9c8\uc874, \uad6c\uae00, \ub9c8\uc774\ud06c\ub85c\uc18c\ud504\ud2b8 \ub4f1 \uc8fc\uc694 \ud074\ub77c\uc6b0\ub4dc \uc11c\ube44\uc2a4 \uc81c\uacf5\uc5c5\uccb4\ub4e4\uc740 \ud22c\uba85\uc131\uc744 \ub192\uc774\uace0 \ubcf4\uc548 \uc870\uce58\ub97c \uac15\ud654\ud558\ub77c\ub294 \uc555\ubc15\uc744 \ubc1b\uc74c.  \ud2b9\ud788 \ub9c8\uc774\ud06c\ub85c\uc18c\ud504\ud2b8\ub294 \uc911\uad6d \uc815\ubd80\uc640 \uc5f0\uacc4\ub41c \uc2a4\ud30c\uc774 \uc791\uc804\uc73c\ub85c \uc778\ud574, \ub9c8\uc774\ud06c\ub85c\uc18c\ud504\ud2b8 \ub124\ud2b8\uc6cc\ud06c\uc758 \ucde8\uc57d\uc810\uc744 \uc545\uc6a9\ud558\uc5ec \ubbfc\uac10\ud55c \uc774\uba54\uc77c \uacc4\uc815\uc5d0 \uc811\uadfc\ud55c \uc0ac\uac74\uc73c\ub85c \uc778\ud574 \uc815\ubc00 \uc870\uc0ac\ub97c \ubc1b\uc74c.",
        "e3cbe666-93f6-4d79-9fe9-36a30ab6c2df": "\uc0b0\uc5c5\uacc4, \uad6d\uc81c \ud30c\ud2b8\ub108 \ubc0f \uae30\ud0c0 \ube44 \uc5f0\ubc29\uae30\uad00\uacfc \ud611\ub825\ud558\uc5ec \ucc45\uc784 \uc788\ub294 AI R&D\uc5d0 \ub300\ud55c \uc9c0\uc18d\uc801\uc778 \ud22c\uc790\uc640 \uc774\ub97c \ud1b5\ud55c \uc5ed\ub7c9 \uac1c\ubc1c \uae30\ud68c\ub97c \ucd09\uc9c4\u2468 AI \uc5f0\uad6c \ubd84\uc57c\uc758 \uad6d\uc81c \ud611\ub825\uc5d0 \ub300\ud55c \uc6d0\uce59\uc801\uc774\uace0 \uc870\uc728\ub41c \uc811\uadfc \ubc29\uc2dd \ud655\ub9bd: \ud658\uacbd\uc801 \uc9c0\uc18d\uac00\ub2a5\uc131, \uc758\ub8cc, \uc81c\uc870 \ub4f1\uacfc \uac19\uc740 \uae00\ub85c\ubc8c \uacfc\uc81c\ub97c \ud574\uacb0\ud558\uae30 \uc704\ud574 AI R&D\uc5d0\uc11c \uad6d\uc81c \ud611\ub825\uc744 \uc6b0\uc120\uc2dc\ud558\uc5ec \uad6d\uc81c \uac00\uc774\ub4dc\ub77c\uc778 \ubc0f \ud45c\uc900 \uac1c\ubc1c, \uc774\ud589\uc744 \uc9c0\uc6d0",
        "ecbdc197-27df-41f0-b8be-a8fdf2767cf4": "25 \n\u2161. ICT \uc774\uc288 Top10  \u2467\ubbf8\uad6d, \uc0ac\uc774\ubc84\ubcf4\uc548 \uac15\ud654\uc5d0 \ubc15\ucc28 \n \ubbf8\uad6d \uc815\ubd80 \uae30\uad00, \ud574\ud0b9 \ud53c\ud574 \ub300\uc751 \uac15\ud654\u2022 \ubbf8\uad6d\uc758 \uc5ec\ub7ec \uae30\uc5c5\uacfc \uc815\ubd80\uae30\uad00\uc774 MOVEIt \ud30c\uc77c \uacf5\uc720 \uc18c\ud504\ud2b8\uc6e8\uc5b4\uc758 \ucde8\uc57d\uc810\uc744 \uc774\uc6a9\ud55c \uc0ac\uc774\ubc84 \uacf5\uaca9\uc744 \ub2f9\ud568. \ub3c4\ub09c\ub2f9\ud55c \ub370\uc774\ud130\uc758 \ubbfc\uac10\ub3c4\uc5d0 \ub300\ud55c \uad6c\uccb4\uc801\uc778 \uc815\ubcf4\ub294 \uc544\uc9c1 \uba85\ud655\ud558\uc9c0 \uc54a\uc73c\ub098, \uc774 \uc0ac\uac74\uc740 \ucd5c\uadfc \uba87 \ub144\uac04 \ubc1c\uc0dd\ud55c \uc5f0\ubc29\uae30\uad00\uc758 \uc138 \ubc88\uc9f8 \uc8fc\uc694 \uce68\ud574 \uc0ac\ub840\uc784\u2022 \uc774\ub7ec\ud55c \uc0ac\uac74\ub4e4\uc740 \uc815\ubd80\uae30\uad00 \ub0b4\uc5d0\uc11c \uc0ac\uc774\ubc84 \ubcf4\uc548 \ud504\ub85c\ud1a0\ucf5c\uc758 \uae34\uae09\ud55c \uc7ac\ud3c9\uac00\ub97c \ucd09\ubc1c\ud558\uba70, \uc815\uad50\ud55c \uc0ac\uc774\ubc84 \uc801\ub300\uc790\ub85c\ubd80\ud130 \ubbfc\uac10\ud55c \uc815\ubcf4\ub97c \ubcf4\ud638\ud558\uae30 \uc704\ud55c \uac15\ub825\ud55c \uc0ac\uc774\ubc84 \ubcf4\uc548 \uc870\uce58\uc758 \ud544\uc694\uc131\uc744 \uac15\uc870\ud568. \uc0ac\uc774\ubc84 \ubcf4\uc548 \ubc0f \uc778\ud504\ub77c \ubcf4\uc548\uad6d(CISA)\uc740 \uc774\ub7ec\ud55c \ud574\ud0b9\uc758 \ubc94\uc704\ub97c \uc801\uadf9\uc801\uc73c\ub85c \uc870\uc0ac\ud558\uba70, \uc5f0\ubc29\uae30\uad00\uc774 \ubc1b\ub294 \uc601\ud5a5\uc744 \ud30c\uc545\ud558\uace0 \uc801\uc2dc\uc5d0 \uc870\uce58\ub97c \ucde8\ud560 \uc218 \uc788\ub3c4\ub85d \uc9c0\uc6d0\ud568\n \ubbf8\uad6d, \uc0c8\ub85c\uc6b4 \uad6d\uac00 \uc0ac\uc774\ubc84 \ubcf4\uc548 \uc804\ub7b5 \ubc1c\ud45c\u2022 \ubc31\uc545\uad00\uc740 2023\ub144 3\uc6d4, \uc99d\uac00\ud558\ub294 \uc0ac\uc774\ubc84 \uc704\ud611\uc5d0 \ub300\ud55c \uad6d\uac00 \ubc29\uc5b4\ub97c \uac15\ud654\ud558\uae30 \uc704\ud574 \uc0c8\ub85c\uc6b4 \uad6d\uac00 \uc0ac\uc774\ubc84 \ubcf4\uc548 \uc804\ub7b5\uc744 \uacf5\uac1c\ud568.",
        "ac13f339-e077-4835-8eed-f363a7078293": "\uc774 \ud30c\ud2b8\ub108\uc2ed\uc740 \uace0\uc131\ub2a5 \ucef4\ud4e8\ud305\uc744 \uada4\ub3c4\uc5d0 \ub3c4\uc785\ud558\uc5ec \uc704\uc131 \uc6b4\uc601 \ubc0f \uc9c0\uad6c \uad00\uce21 \ubd84\uc11d\uc5d0\uc11c \uc2e4\uc2dc\uac04 \uc758\uc0ac\uacb0\uc815\uc5d0 \ud544\uc218\uc801\uc778 \ub370\uc774\ud130 \ucc98\ub9ac \ubc0f \ubd84\uc11d\uc744 \uac00\ub2a5\ud558\uac8c \ud568\u2022 AWS\ub294 \uc704\uc131\uc5d0\uc11c \ub370\uc774\ud130\ub97c \ucc98\ub9ac\ud558\uace0 \ubd84\uc11d\ud558\uc5ec \uac00\uc7a5 \uc720\uc6a9\ud55c \uc774\ubbf8\uc9c0\ub9cc \ub2e4\uc6b4\ub9c1\ud06c\ud558\ub294 \ubc29\uc2dd\uc73c\ub85c \uada4\ub3c4 \ub0b4 \uc778\uacf5\uc9c0\ub2a5(AI) \ubc0f \uba38\uc2e0\ub7ec\ub2dd(ML) \ub2a5\ub825\uc744 \uc131\uacf5\uc801\uc73c\ub85c \uc2dc\uc5f0\ud568. \uc774\ub7ec\ud55c \ubc1c\uc804\uc740 \ub370\uc774\ud130 \uc804\uc1a1\uc5d0 \ud544\uc694\ud55c \ub300\uc5ed\ud3ed\uc744 \uc904\uc774\uace0 \uc704\uc131 \uc6b4\uc601\uc758 \ud6a8\uc728\uc131\uc744 \ucd5c\uc801\ud654\ud558\ub294 \uac83\uc740 \ubb3c\ub860, \uc9c0\uad6c\uc5d0 \ub3c4\ub2ec\ud558\uae30 \uc804\uc5d0 \ubd88\ud544\uc694\ud55c \ub370\uc774\ud130\ub97c \ud544\ud130\ub9c1\ud568\uc73c\ub85c\uc368 \uc6b0\uc8fc \ub370\uc774\ud130 \uad00\ub9ac\uc758 \uc0c8\ub85c\uc6b4 \uae30\uc900\uc744 \uc81c\uc2dc\ud568\n \ub9c8\uc774\ud06c\ub85c\uc18c\ud504\ud2b8, \uc2a4\ud398\uc774\uc2a4 \uc5d1\uc2a4\uc640 \uc6b0\uc8fc \ud074\ub77c\uc6b0\ub4dc \uc11c\ube44\uc2a4 \uac1c\ubc1c\u2022 \ub9c8\uc774\ud06c\ub85c\uc18c\ud504\ud2b8(Microsoft)\ub294 Azure Space \uc774\ub2c8\uc154\ud2f0\ube0c\ub97c \ud1b5\ud574 \uc2a4\ud0c0\ub9c1\ud06c(Starlink) \uc704\uc131 \uc778\ud130\ub137 \uc11c\ube44\uc2a4\ub97c \uc704\ud55c \ud074\ub77c\uc6b0\ub4dc \uc11c\ube44\uc2a4\ub97c \uc81c\uacf5\ud558\uae30 \uc704\ud574 \uc2a4\ud398\uc774\uc2a4 \uc5d1\uc2a4(SpaceX)\uc640 \uc804\ub7b5\uc801 \ud30c\ud2b8\ub108\uc2ed\uc744 \uccb4\uacb0\ud568.",
        "35e24ac0-4869-4a51-a060-75cc08ca3bd6": "AI\uc704\ud5d8 \uace0\ub824 \uc81c\uace0 \uc704\ud55c \uac1c\uc778\uc815\ubcf4 \uc9c0\uce68 \uac15\ud654\u2023 \uc5f0\ubc29\uae30\uad00\uc774 \uac1c\uc778\uc815\ubcf4\ubcf4\ud638 \uae30\uc220\uc758 \ud6a8\uacfc\ub97c \ud3c9\uac00\ud560 \uc218 \uc788\ub294 \uc9c0\uce68 \uac1c\ubc1c\ud615\ud3c9\uc131 \ubc0f \uc2dc\ubbfc\uad8c \uc99d\uc9c4\u2023 AI \uc54c\uace0\ub9ac\uc998\uc774 \ucc98\ubc8c\uc744 \uc720\ub3c4\ud558\uc9c0 \uc54a\ub3c4\ub85d \uc5f0\ubc29\uae09\uc5ec \ud504\ub85c\uadf8\ub7a8, \uc5f0\ubc29 \uacc4\uc57d\uc790\uc5d0\uac8c \uba85\ud655\ud55c \uc9c0\uce68\uc744 \uc81c\uacf5\u2023 AI\uc640 \uad00\ub828\ub41c \ubbfc\uad8c \uce68\ud574\uc870\uc0ac \ubc0f \ubaa8\ubc94\uc0ac\ub840 \uad50\uc721 \ub4f1\uc744 \ud1b5\ud574 \uc54c\uace0\ub9ac\uc998\uc758 \ucc28\ubcc4 \ud574\uc18c\u2023 \ubc94\uc8c4 \uc608\uce21, \ud3ec\ub80c\uc2dd, \uc704\ud5d8\uc131 \ud3c9\uac00 \ub4f1 AI \uc0ac\uc6a9 \ubaa8\ubc94\uc0ac\ub840\ub97c \uac1c\ubc1c, \ud615\uc0ac \uc0ac\ubc95\uc81c\ub3c4 \uc804\ubc18\uc758 \uacf5\uc815\uc131 \ubcf4\uc7a5\uc18c\ube44\uc790, \ud658\uc790, \ud559\uc0dd\uc744 \uc704\ud55c \uc9c0\uc6d0\u2023 \uc758\ub8cc \ubd84\uc57c\uc5d0\uc11c AI\uc758 \ucc45\uc784\uac10 \uc788\ub294 \uc0ac\uc6a9 \ucd09\uc9c4, AI \uad00\ub828 \uc758\ub8cc \ubd84\uc57c \uc704\ud5d8 \ubcf4\uace0 \uccb4\uacc4 \uc218\ub9bd\u2023 AI \uc9c0\uc6d0 \uad50\uc721 \ub3c4\uad6c \ubc30\ud3ec \uc9c0\uc6d0\n\uadfc\ub85c\uc790 \uc9c0\uc6d0\u2023 \uc77c\uc790\ub9ac \ub300\uccb4, \ub178\ub3d9 \uae30\uc900, \uc9c1\uc7a5 \ub0b4 \ud615\ud3c9\uc131, \uac74\uac15, \uc548\uc804, \ub370\uc774\ud130 \uc218\uc9d1 \ubb38\uc81c\ub97c \ud574\uacb0\ud568\uc73c\ub85c\uc368 \uadfc\ub85c\uc790\uc5d0\uac8c AI\uc758 \ud53c\ud574\ub97c \uc644\ud654\ud558\uace0 \uc774\uc810\uc744 \uadf9\ub300\ud654\ud558\uae30 \uc704\ud55c \uc6d0\uce59\uacfc \ubaa8\ubc94\uc0ac\ub840 \uac1c\ubc1c\u2023 AI\uc758 \ub178\ub3d9\uc2dc\uc7a5\uc5d0 \ub300\ud55c \uc7a0\uc7ac\uc801 \uc601\ud5a5\ub825 \ubcf4\uace0\uc11c \uc791\uc131,",
        "798ad9fd-61ec-4efb-a048-bc3c185968b6": "\uc6d4\ub9c8\ud2b8\uc758 \ub4dc\ub860 \ubc30\uc1a1 \uc11c\ube44\uc2a4\ub294 DFW \uc9c0\uc5ed \uc804\uccb4 \uc778\uad6c\uc758 75%\uc5d0 \ud574\ub2f9\ud558\ub294 1,800\ub9cc \uac00\uad6c\uc5d0 \uc11c\ube44\uc2a4\ub97c \uc81c\uacf5\ud560 \uc608\uc815\uc774\uba70, \uc774 \uc11c\ube44\uc2a4\ub294 \uace0\uac1d\uc774 \uc6d0\ud558\ub294 \uc0c1\ud488\uc744 \uba87 \ubd84 \ub9cc\uc5d0 \ubc1b\uc544\ubcfc \uc218 \uc788\ub3c4\ub85d \ud3b8\uc758\uc131\uc744 \uadf9\ub300\ud654\ud568\u2022 \uc544\ub9c8\uc874\uc740 \ud14d\uc0ac\uc2a4\uc8fc \uce7c\ub9ac\uc9c0 \uc2a4\ud14c\uc774\uc158(College Station)\uc5d0\uc11c \uc544\ub9c8\uc874 \uc57d\uad6d \uace0\uac1d\uc744 \ub300\uc0c1\uc73c\ub85c \ub4dc\ub860\uc744 \uc774\uc6a9\ud55c \ucc98\ubc29\uc57d \ubc30\uc1a1 \uc11c\ube44\uc2a4\ub97c \uc2dc\uc791\ud568. \uc774 \uc11c\ube44\uc2a4\ub97c \ud1b5\ud574 \uace0\uac1d\uc740 60\ubd84 \uc774\ub0b4\uc5d0 500\uc5ec \uac00\uc9c0\uc758 \uc57d\ud488\uc744 \ubc30\uc1a1\ubc1b\uc744 \uc218 \uc788\uc73c\uba70, \uc544\ub9c8\uc874\uc740 \ub4dc\ub860 \ubc30\uc1a1\uc758 \uac00\ub2a5\uc131\uc744 \ub113\ud788\uace0 \uace0\uac1d\uc5d0\uac8c \ub354\uc6b1 \ube60\ub974\uace0 \ud3b8\ub9ac\ud55c \uc11c\ube44\uc2a4\ub97c \uc81c\uacf5\ud568\n \uc9d1\ub77c\uc778\uacfc \uc719, \uace0\ub3c4\uc758 \ub4dc\ub860 \ubc30\uc1a1 \uae30\uc220 \uac1c\ubc1c\u2022 \uc9d1\ub77c\uc778(Zipline)\uc740 \ucc28\uc138\ub300 \ub4dc\ub860 \ubc30\uc1a1 \uc2dc\uc2a4\ud15c\uc744 \uacf5\uac1c\ud558\uba70, \uc815\ubc00 \ubc30\uc1a1\uc774 \uac00\ub2a5\ud55c \uc790\uc728\uc8fc\ud589 \ub4dc\ub85c\uc774\ub4dc\ub97c \ud14c\ub354\ub85c \ub0ae\ucd94\uc5b4 \uc815\ud655\ud55c \uc704\uce58\uc5d0 \ubb3c\ud488\uc744 \ubc30\uc1a1\ud568.",
        "1101237d-9eab-45c0-a655-ba619a882322": "\uc81c\uc870 \uc778\ub825 \ubc0f \uc5f0\uad6c\uc790 \uc9c0\uc6d0, \ucee4\ub9ac\ud058\ub7fc \uac1c\ubc1c\uc5d0 \ucd08\uc810\uc744 \ub9de\ucd98 \uc0c8\ub85c\uc6b4 \uacc4\ud68d\uc744 \ud1b5\ud574 \ubbf8\uad6d \ubc18\ub3c4\uccb4 \uc778\ub825 \ud22c\uc790\u2023 \ubc18\ub3c4\uccb4 \uae30\uc5c5\uc758 \uc815\uaddc\uc9c1 \ucc44\uc6a9\uc5d0 \uc9c0\uc6d0\ud55c \ud559\uc0dd \uc218\ub294 2022~2023\ub144\uc5d0 79% \uc99d\uac00\n\ud601\uc2e0 \ud22c\uc790\u2023 \uc0c1\ubb34\ubd80\ub294 \uae30\ud0c0 \ubd80\ucc98\ub4e4\uacfc \uad6d\ub9bd \ubc18\ub3c4\uccb4 \uae30\uc220 \uc13c\ud130 \uc124\ub9bd \ucd94\uc9c4\u2023 \uc0c1\ubb34\ubd80\ub294 110\uc5b5 \ub2ec\ub7ec \uaddc\ubaa8\uc758 R&D \uc790\uae08\uc744 \uacc4\uce21 \ud504\ub85c\uadf8\ub7a8, \uad6d\ub9bd \uace0\uae09 \ud3ec\uc7a5 \uc81c\uc870 \ud504\ub85c\uadf8\ub7a8, \ucd5c\ub300 3\uac1c\uc758 \uc2e0\uaddc \u2018Manufacturing USA\u2019 \uc5f0\uad6c\uc18c \ub4f1 \uae30\ud0c0 \ubd80\ubb38\uc5d0\ub3c4 \ud22c\uc790\u2023 \uad6d\ubc29\ubd80\ub294 \ub9c8\uc774\ud06c\ub85c\uc804\uc790\uacf5\ud559 \uacf5\uc6a9 R&D \ud504\ub85c\uadf8\ub7a8\uc5d0 \ub300\ud55c \uc194\ub8e8\uc158 \uc694\uccad\uc11c \ubc1c\ud45c\n\uc9c0\uc5ed \uacbd\uc81c \uac1c\ubc1c \ubc0f \ud601\uc2e0 \uc9c0\uc6d0\u2023 \uc0c1\ubb34\ubd80\ub294 5\uc5b5 \ub2ec\ub7ec \uaddc\ubaa8\uc758 \uae30\uc220 \ud5c8\ube0c \ud504\ub85c\uadf8\ub7a8 1\ub2e8\uacc4\ub97c \uc704\ud55c \uc790\uae08 \uc870\ub2ec \uae30\ud68c \ubc1c\ud45c\u2023 \ub099\ud6c4 \uc9c0\uc5ed \uacbd\uc81c\ubc1c\uc804 \ubc0f \uc77c\uc790\ub9ac \ucc3d\ucd9c\uc744 \uc704\ud55c Recompete \ud504\ub85c\uadf8\ub7a8 1\ub2e8\uacc4\uc5d0 2\uc5b5 \ub2ec\ub7ec \uc790\uae08 \uc870\ub2ec \uae30\ud68c \ubc1c\ud45c\u2023 \uad6d\ub9bd\uacfc\ud559\uc7ac\ub2e8\uc740 \uae30\uc220, \ud601\uc2e0,",
        "99e80918-fac0-4a22-bb42-b9d87d8505b0": "\ubbf8\uad6d",
        "1e29e1e5-089e-4703-a6ac-95e6a2584435": "\ubc31\uc545\uad00\uc740 \ubcf4\ub3c4\uc790\ub8cc\ub97c \ud1b5\ud574 \ud55c\uad6d, \ud638\uc8fc, \ube0c\ub77c\uc9c8, \uce90\ub098\ub2e4, \uce60\ub808, \ud504\ub791\uc2a4, \u200b\u200b\ub3c5\uc77c, \uc778\ub3c4, \uc720\ub7fd\uc5f0\ud569(EU) \ub4f1 20\uac1c\uad6d\uc744 \uc5b8\uae09\ud568[\ud45c 6] AI \uc548\uc804 \uc11c\uc57d 3\uac00\uc9c0 \uc6d0\uce59\uc6d0\uce59 \uc138\ubd80 \uc870\ud56d\ucd9c\uc2dc \uc804 \uc81c\ud488 \uc548\uc804\uc131 \ubcf4\uc7a5\u2023 \uae30\uc5c5\uc740 AI \uc2dc\uc2a4\ud15c \ucd9c\uc2dc \uc804\uc5d0 \ub0b4\u00b7\uc678\ubd80 \ubcf4\uc548 \ud14c\uc2a4\ud2b8 \uc57d\uc18d\u2023 \uae30\uc5c5\uc740 AI \uc704\ud5d8 \uad00\ub9ac\uc5d0 \uad00\ud55c \uc815\ubcf4\ub97c \uc5c5\uacc4 \uc804\ubc18, \uc815\ubd80, \uc2dc\ubbfc \uc0ac\ud68c, \ud559\uacc4\uc640 \uacf5\uc720\ud558\uae30 \uc704\ud574 \ucd5c\uc120\uc744 \ub2e4\ud560 \uac83 \uc57d\uc18d\n\ubcf4\uc548\uc744 \ucd5c\uc6b0\uc120\uc73c\ub85c \ud558\ub294 \uc2dc\uc2a4\ud15c \uad6c\ucd95\u2023 \ud68c\uc0ac\ub294 \ub3c5\uc810\u00b7\ubbf8\uacf5\uac1c \ubaa8\ub378 \uac00\uc911\uce58 \ubcf4\ud638\ub97c \uc704\ud574 \uc0ac\uc774\ubc84\ubcf4\uc548 \ubc0f \ub0b4\ubd80 \uc704\ud611 \ubcf4\ud638 \uc7a5\uce58\uc5d0 \ud22c\uc790\ud558\uae30\ub85c \uc57d\uc18d\u2023 \uae30\uc5c5\uc740 AI \uc2dc\uc2a4\ud15c\uc758 \ucde8\uc57d\uc810\uc744 \uc81c3\uc790\uac00 \uc27d\uac8c \ubc1c\uacac\ud558\uace0 \ubcf4\uace0\ud560 \uc218 \uc788\ub3c4\ub85d \uc804\ub150\n\ub300\uc911\uc758 \uc2e0\ub8b0 \ud68d\ub4dd\n\u2023 \uae30\uc5c5\uc740 \uc6cc\ud130\ub9c8\ud0b9 \uc2dc\uc2a4\ud15c \ub4f1 \ucf58\ud150\uce20\uc758 AI \uc0dd\uc131 \uc2dc\uae30\ub97c \uc0ac\uc6a9\uc790\uac00 \uc54c \uc218 \uc788\ub3c4\ub85d \uac15\ub825\ud55c \uae30\uc220 \uba54\ucee4\ub2c8\uc998\uc744 \uac1c\ubc1c\ud558\uae30 \uc704\ud574 \ub178\ub825\u2023 \uae30\uc5c5\uc740 AI \uc2dc\uc2a4\ud15c\uc758 \uae30\ub2a5, \ud55c\uacc4,",
        "67a9e33e-5f42-4bf6-86f5-a5509dcf9033": "\uc774 \ud30c\ud2b8\ub108\uc2ed\uc740 \uc2a4\ud0c0\ub9c1\ud06c \uc704\uc131\uc5d0 \uc5f0\uacb0\ub418\ub294 \uad6c\uae00(Google) \ub370\uc774\ud130 \uc13c\ud130 \ub0b4\uc758 \uc9c0\uc0c1 \uc2a4\ud14c\uc774\uc158 \uc124\uce58\ub97c \ud3ec\ud568\ud558\uba70, \uad6c\uae00 \ud074\ub77c\uc6b0\ub4dc\ub97c \ud1b5\ud574 \ube60\ub974\uace0 \uc548\uc804\ud558\uba70 \uc2e0\ub8b0\ud560 \uc218 \uc788\ub294 \ud074\ub77c\uc6b0\ub4dc \uc11c\ube44\uc2a4\ub97c \uc81c\uacf5\ud558\uace0\uc790 \ud568\u2022 \ub9c8\uc774\ud06c\ub85c\uc18c\ud504\ud2b8\ub294 \uc2a4\ud398\uc774\uc2a4 \uc5d1\uc2a4\uc640\uc758 \ud611\ub825 \uc678\uc5d0\ub3c4 \ub9dd\uac00\ud0c0 \ub124\ud2b8\uc6cc\ud06c(Mangata Networks)\uc640 \ud30c\ud2b8\ub108\uc2ed\uc744 \uccb4\uacb0\ud558\uc5ec \uc704\uc131\uc744 \ud1b5\ud55c AI \uc9c0\uc6d0 \uc5e3\uc9c0 \ud074\ub77c\uc6b0\ub4dc \uc5f0\uacb0\uc744 \uc120\ub3c4\ud568. \uae00\ub85c\ubc8c \uace0\uc18d \uc800\uc9c0\uc5f0 \uc704\uc131 \uc5f0\uacb0 \ubc0f \uace0\uae09 \uc5d0\uc9c0 \ucef4\ud4e8\ud2b8 \uc194\ub8e8\uc158\uc744 \ud1b5\ud574 \ub9c8\uc774\ud06c\ub85c\uc18c\ud504\ud2b8 Azure \ud074\ub77c\uc6b0\ub4dc\uc758 \ub3c4\ub2ec \ubc94\uc704\uc640 \uae30\ub2a5\uc744 \ud5a5\uc0c1\uc2dc\ud0a4\ub294 \uac83\uc744 \ubaa9\ud45c\ub85c \ud568\n IBM\uacfc \uc6b0\uc8fc \ub370\uc774\ud130 \ucc98\ub9ac \ud601\uc2e0 \uae30\uc5ec\u2022 IBM\uc740 \uc720\ubcf4\ud2f0\uce74(Ubotica)\uc640 \ud611\ub825\ud558\uc5ec \uc800\uc9c0\uad6c \uada4\ub3c4(LEO) \uc704\uc131\uc5d0 \ud0d1\uc7ac\ub41c AI \uc560\ud50c\ub9ac\ucf00\uc774\uc158\uc758 \ubc30\ud3ec\ub97c \ub2e8\uc21c\ud654\ud558\ub294 \uc784\ubb34\uc5d0 \ucc29\uc218\ud568. \uc774 \ud30c\ud2b8\ub108\uc2ed\uc740 IBM\uc758 \ud074\ub77c\uc6b0\ub4dc \uc778\ud504\ub77c\uc640 watsonx.ai \uad6c\uc131 \uc694\uc18c\ub97c \ud65c\uc6a9\ud558\uc5ec \uc704\uc131\uc5d0 AI \ubaa8\ub378\uc744 \uc9c1\uc811 \uc6d0\ud074\ub9ad\uc73c\ub85c \ubc30\ud3ec\ud560 \uc218 \uc788\uac8c \ud568.",
        "19ef3369-ef4e-413f-b0a3-f1ddec2a8b6e": "17",
        "67a11feb-e62c-4821-8fbc-c97cc7df6e4a": "\uc0ac\uc774\ubc84 \ubcf4\uc548 \ubc0f \uc778\ud504\ub77c \ubcf4\uc548\uad6d(CISA)\uc740 \uc774\ub7ec\ud55c \ud574\ud0b9\uc758 \ubc94\uc704\ub97c \uc801\uadf9\uc801\uc73c\ub85c \uc870\uc0ac\ud558\uba70, \uc5f0\ubc29\uae30\uad00\uc774 \ubc1b\ub294 \uc601\ud5a5\uc744 \ud30c\uc545\ud558\uace0 \uc801\uc2dc\uc5d0 \uc870\uce58\ub97c \ucde8\ud560 \uc218 \uc788\ub3c4\ub85d \uc9c0\uc6d0\ud568\n \ubbf8\uad6d, \uc0c8\ub85c\uc6b4 \uad6d\uac00 \uc0ac\uc774\ubc84 \ubcf4\uc548 \uc804\ub7b5 \ubc1c\ud45c\u2022 \ubc31\uc545\uad00\uc740 2023\ub144 3\uc6d4, \uc99d\uac00\ud558\ub294 \uc0ac\uc774\ubc84 \uc704\ud611\uc5d0 \ub300\ud55c \uad6d\uac00 \ubc29\uc5b4\ub97c \uac15\ud654\ud558\uae30 \uc704\ud574 \uc0c8\ub85c\uc6b4 \uad6d\uac00 \uc0ac\uc774\ubc84 \ubcf4\uc548 \uc804\ub7b5\uc744 \uacf5\uac1c\ud568. \uc774 \uc804\ub7b5\uc740 \ubcd1\uc6d0, \uc5d0\ub108\uc9c0 \uc2dc\uc124 \ub4f1 \ud575\uc2ec \uc778\ud504\ub77c\ub97c \ubcf4\ud638\ud558\uace0, \ub514\uc9c0\ud138 \uc0dd\ud0dc\uacc4 \uc704\ud611\uc5d0 \ub300\uc751\ud558\uae30 \uc704\ud574 UN\uacfc\uc758 \ud611\ub825\uc744 \uac15\ud654\ud568. \uc870 \ubc14\uc774\ub4e0(Joe Biden) \ubbf8\uad6d \ub300\ud1b5\ub839\uc740 \uc77c\uc0c1\uacfc \uad6d\uac00 \uc548\ubcf4\ub97c \ub4b7\ubc1b\uce68\ud558\ub294 \ub514\uc9c0\ud138 \uc778\ud504\ub77c\uc5d0 \ub300\ud55c \uc2e0\ub8b0\uc758 \uc911\uc694\uc131\uc744 \uac15\uc870\ud558\uba70, \uacf5\uaca9\ubcf4\ub2e4 \ubc29\uc5b4\uac00 \uc6a9\uc774\ud55c \ud0c4\ub825\uc801\uc778 \ub514\uc9c0\ud138 \uc0dd\ud0dc\uacc4\ub97c \uad6c\ucd95\ud558\ub294 \uc804\ub7b5\uc758 \ubaa9\ud45c\ub97c \uac15\uc870\ud568\u2022 \uc774 \uc804\ub7b5\uc740 \uc0ac\uc774\ubc84 \uc704\ud611 \ud574\uacb0\uc744 \uc704\ud55c 5\uac1c\uc758 \ud575\uc2ec\uc744 \uc81c\uc2dc\ud568. \uc5ec\uae30\uc5d0\ub294 \ud575\uc2ec \uae30\ubc18 \uc2dc\uc124 \ubc29\uc5b4, \uc704\ud611 \ud589\uc704\uc790 \uad50\ub780, \ubcf4\uc548 \ubc0f \ud68c\ubcf5\ub825\uc744 \ucd09\uc9c4\ud558\uae30 \uc704\ud55c \uc2dc\uc7a5 \uc138\ub825 \ud615\uc131, \ud68c\ubcf5\ub825 \uc788\ub294 \ubbf8\ub798\uc5d0 \ub300\ud55c \ud22c\uc790, \uad6d\uc81c \ud30c\ud2b8\ub108\uc2ed \uad6c\ucd95\uc774 \ud3ec\ud568\ub428.",
        "80b5de65-d555-4194-90d8-18f499516714": "10 \n\u2160. ICT \uad6d\uac00 \uc0b0\uc5c5 \ud604\ud669 3.ICT \uc8fc\uc694\uc815\ucc45  \u2461 AI \uc548\uc804 \uc11c\uc57d(Summit on AI Safety)\n AI \uae30\uc5c5\uc758 \uc548\uc804\ud55c \uc5f0\uad6c\uac1c\ubc1c\uc744 \uc704\ud55c \uc11c\uc57d \u2022 2023\ub144 7\uc6d4, \uc870 \ubc14\uc774\ub4e0(Joe Biden) \ub300\ud1b5\ub839\uc740 AI \uae30\uc220\uc744 \uac1c\ubc1c\ud558\ub294 \uc8fc\uc694 \uae30\uc5c5\uc774 \uc0c8\ub85c\uc6b4 \uae30\uc220\uacfc \uc2dc\uc2a4\ud15c\uc744 \uc124\uacc4\uff65\uacf5\uc720\uff65\ud14c\uc2a4\ud2b8\ud558\ub294 \uc5f0\uad6c\uac1c\ubc1c \uacfc\uc815\uc5d0 \ud544\uc694\ud55c 3\uac00\uc9c0 \uc6d0\uce59\uacfc 8\uac00\uc9c0 \uc138\ubd80 \uc870\ud56d\uc73c\ub85c \uc774\ub8e8\uc5b4\uc9c4 \u2018AI \uc548\uc804 \uc11c\uc57d(Summit on AI Safety)\u2019\uc744 \ubc1c\ud45c\ud568\u2022 AI \uc548\uc804 \uc11c\uc57d\uc740 \u25b2\uc548\uc804 \u25b2\ubcf4\uc548 \u25b2\uc2e0\ub8b0 \ub4f1 3\uac00\uc9c0 \uc6d0\uce59\uc744 \uae30\ubc18\uc73c\ub85c \ucc45\uc784\uac10 \uc788\ub294 AI(Responsible AI) \uac1c\ubc1c\uc744 \ucd94\uc9c4\ud558\ub294 \uac83\uc744 \ubaa9\uc801\uc73c\ub85c \ud568\u2022 \uc624\ud508AI(OpenAI), \uad6c\uae00(Google), \ub9c8\uc774\ud06c\ub85c\uc18c\ud504\ud2b8(Microsoft), \uba54\ud0c0(Meta), \uc544\ub9c8\uc874(Amazon), \uc564\ud2b8\ub85c\ud53d(Anthropic), \uc778\ud50c\ub809\uc158AI(InflectionAI) \ub4f1 \ub300\ud615\uc5b8\uc5b4\ubaa8\ub378(LLM)\uc744 \ubcf4\uc720\ud55c \uc8fc\uc694 \uae30\uc5c5 7\uacf3\uc774 AI \uc548\uc804 \uc11c\uc57d\uc5d0 \ub3d9\uc758\ud568\u2022 \ubbf8\uad6d \ud589\uc815\ubd80\ub294 \uc790\uad6d\uc5d0\uc11c AI \uc548\uc804 \uc11c\uc57d \uc758\uc81c\ub97c \uc9c4\uc804\uc2dc\ud0a4\uace0, \ub3d9\ub9f9\uad6d \ubc0f \ud30c\ud2b8\ub108\uc640 \ud611\ub825\ud558\uc5ec AI \uac1c\ubc1c \ubc0f \uc0ac\uc6a9\uc744 \uad00\ub9ac\ud558\uae30 \uc704\ud55c \uad6d\uc81c \ud504\ub808\uc784\uc6cc\ud06c\ub97c \uad6c\ucd95\ud560 \uc608\uc815\uc784. \ubc31\uc545\uad00\uc740 \ubcf4\ub3c4\uc790\ub8cc\ub97c \ud1b5\ud574 \ud55c\uad6d, \ud638\uc8fc, \ube0c\ub77c\uc9c8, \uce90\ub098\ub2e4, \uce60\ub808, \ud504\ub791\uc2a4,",
        "a21fff63-441e-4cb3-8295-119d0308d2a4": "28 \n[\ucc38\uace0\ubb38\ud5cc]\n\u25a0\ucc38\uace0 \uc790\ub8cc\n1.\uc678\uad50\ubd80, \u300c\uad6d\uac00\uac1c\ud669\u300d, 20232.\uc138\uacc4\uc9c0\uc801\uc7ac\uc0b0\uad8c\uae30\uad6c(WIPO), \u300cGlobal Innovation Index 2023\u300d, 2023\n\u25a0\ucc38\uace0 \uc0ac\uc774\ud2b81.\uad6d\uac00\ud1b5\uc2e0\uc815\ubcf4\uad00\ub9ac\uccad(NTIA)(www.ntia.doc.gov)2.\uc5f0\ubc29\ud1b5\uc2e0\uc704\uc6d0\ud68c(FCC)(www.fcc.gov)3.\uad6d\uac00\uacfc\ud559\uae30\uc220\uc704\uc6d0\ud68c(NSTC)(www.whitehouse.gov/ostp/nstc/)4.\ubbf8\uad6d \ubc31\uc545\uad00(www.whitehouse.gov)5AI\ud0c0\uc784\uc988(www.aitimes.com)6.CNBC(www.cnbc.com)7.\uc804\uc790\ub274\uc2a4(www.etnews.com)8.\uc544\uc774\ub274\uc2a424(www.inews24.com)9.Companies Marketcap(companiesmarketcap.com)10.search engine journal(www.searchenginejournal.com)11.nytimes(www.nytimes.com)12.the verge(www.theverge.com)13.zdnet(www.zdnet.com)14.dataconomy(dataconomy.com)15.Wall Street Journal(www.wsj.com)16.uchicago(news.uchicago.edu)17.purdue(www.purdue.edu)18.nsr(www.nsr.com)19.satellite today(www.satellitetoday.com)20.hindustantimes(tech.hindustantimes.com)21.prnewswire(www.prnewswire.com)22.walmart(corporate.walmart.com)23.axios(www.axios.com)24.Finance Yahoo(finance.yahoo.com)25.foxbusiness(www.foxbusiness.com)26.healthcare it news(www.healthcareitnews.com)27.toms hardware(www.tomshardware.com)28.fortune(fortune.com)29.",
        "df5bc443-f027-4ea5-8ab2-6aa26ab5f469": "\uc774\ub294 AI\ub97c \uc77c\uc0c1\uc801\uc778 \uc758\ub8cc \uad00\ud589\uc5d0 \ud1b5\ud569\ud558\ub294 \uc911\uc694\ud55c \ub2e8\uacc4\uc774\uba70, \uc758\ub8cc \uc870\uc5b8\uc758 \ud488\uc9c8\uc744 \ud5a5\uc0c1\uc2dc\ud0a4\uace0 \uc804\ubb38\uac00 \uc9c0\uc2dd\uc744 \ubcf4\ub2e4 \uc811\uadfc \uac00\ub2a5\ud558\uace0 \ud6a8\uc728\uc801\uc73c\ub85c \ub9cc\ub4e4\uc5b4 \uc758\ub8cc \uc0b0\uc5c5\uc744 \ubcc0\ud654\uc2dc\ud0ac \uc7a0\uc7ac\ub825\uc744 \uac00\uc9d0\u2022 \ub85c\uc2a4\uc564\uc824\ub808\uc2a4 \uc5b4\ub9b0\uc774 \ubcd1\uc6d0(Children's Hospital Los Angeles)\uc740 \ubc14\uc774\ud0c8(Vital)\uacfc \ud611\ub825\ud558\uc5ec \uac1c\ubc1c\ud55c AI \uae30\ubc18 ER \ud658\uc790 \uc571, ERAdvisor\ub97c \ub3c4\uc785\ud568. \uc774 \uc571\uc740 \uc18c\uc544 \uc751\uae09 \ubc29\ubb38 \uc911 \ub300\uae30 \uc2dc\uac04, \uc2e4\ud5d8\uc2e4 \uacb0\uacfc, \uc601\uc0c1 \uacb0\uacfc \ubc0f \ud1f4\uc6d0 \uc9c4\ud589 \uc0c1\ud669\uc5d0 \ub300\ud55c \uc2e4\uc2dc\uac04 \uc5c5\ub370\uc774\ud2b8\ub97c \uc81c\uacf5\ud558\uc5ec \ud658\uc790\uc640 \uac00\uc871\uc758 \uacbd\ud5d8\uc744 \uac1c\uc120\ud558\ub294 \uac83\uc744 \ubaa9\ud45c\ub85c \ud568\n \uc758\ub8cc AI \uc5f0\uad6c \ubc0f \uac1c\ubc1c\uc5d0 \ub300\ud55c \uc9c0\uc18d\uc801\uc778 \ud22c\uc790\uc640 \ud611\ub825\u2022 UC \uc0cc\ub514\uc5d0\uc774\uace0 \ud5ec\uc2a4(UC San Diego Health)\ub294 \ud658\uc790 \ud3ec\ud138\uc5d0\uc11c \uc790\ub3d9\uc73c\ub85c \uba54\uc2dc\uc9c0 \uc751\ub2f5 \ucd08\uc548\uc744 \uc791\uc131\ud558\uae30 \uc704\ud574 \uc5d0\ud53d(Epic)\uacfc \ub9c8\uc774\ud06c\ub85c\uc18c\ud504\ud2b8(Microsoft)\uc758 \uc0dd\uc131 AI \uae30\uc220\uc744 \ud1b5\ud569\ud558\ub294 \ud30c\uc77c\ub7ff \ud504\ub85c\uadf8\ub7a8\uc744 \uc2dc\uc791\ud568.",
        "0157601f-ca05-439b-9bc6-83869ba59d26": "19 \n\u2161. ICT \uc774\uc288 Top10 \u2461\ubbf8\uad6d, \uc77c\ubcf8\uacfc \uc591\uc790\ucef4\ud4e8\ud305 \uac1c\ubc1c \ud611\ub825\n \uc591\uad6d \uc815\uc0c1, \uc591\uc790\ucef4\ud4e8\ud305 \ubc0f \ucca8\ub2e8 \uae30\uc220 \ud611\ub825 \uac15\ud654\uc5d0 \uc8fc\ub825\u2022 \uae30\uc2dc\ub2e4 \ud6c4\ubbf8\uc624 \uc77c\ubcf8 \ucd1d\ub9ac\uc640 \uc870 \ubc14\uc774\ub4e0 \ubbf8\uad6d \ub300\ud1b5\ub839\uc740 \ud788\ub85c\uc2dc\ub9c8 \ud68c\ub2f4\uc5d0\uc11c \ubc18\ub3c4\uccb4, \uc778\uacf5\uc9c0\ub2a5, \ud2b9\ud788 \uc591\uc790\ucef4\ud4e8\ud305 \ubd84\uc57c\uc5d0\uc11c\uc758 \ud611\ub825\uc758 \uc911\uc694\uc131\uc744 \uac15\uc870\ud568. \uc774\ub294 \ubca0\uc774\uc9d5\uc758 \uc8fc\uc7a5\uc801 \ud589\ub3d9\uacfc \uc99d\uac00\ud558\ub294 \ubbf8-\uc911 \uae30\uc220 \uacbd\uc7c1\uc5d0 \ub300\uc751\ud558\uae30 \uc704\ud55c \uc804\ub7b5\uc801 \ub178\ub825\uc73c\ub85c \ud3c9\uac00\ub428. \ub450 \uc815\uc0c1\uc740 \uc778\ub3c4-\ud0dc\ud3c9\uc591 \uc9c0\uc5ed\uc758 \ud3c9\ud654\uc640 \uc548\uc815\uc758 \uae30\ubc18\uc73c\ub85c\uc11c \ud55c\ubbf8 \ub3d9\ub9f9\uc758 \uc911\uc694\uc131\uc744 \uac15\uc870\ud558\uba70 \uacf5\ub3d9 \uac00\uce58\uc640 \uc9d1\ub2e8 \uc548\ubcf4\uc758 \uc911\uc694\uc131\uc744 \uac15\uc870\ud568\u2022 \uc591\uad6d \uc815\uc0c1\uc740 \ub610\ud55c, \ub7ec\uc2dc\uc544\uc758 \uce68\ub7b5\uc5d0 \ub9de\uc11c \uc6b0\ud06c\ub77c\uc774\ub098\ub97c \uc9c0\uc6d0\ud558\uace0 \uc9c0\uc5ed \uc548\ubcf4 \uacfc\uc81c\uc5d0 \ub300\uc751\ud558\uae30 \uc704\ud574 \ud611\ub825\ud558\uae30\ub85c \ud569\uc758\ud568. \uc5ec\uae30\uc5d0\ub294 \ubd81\ud55c\uc758 \ud575 \ubc0f \ud0c4\ub3c4\ubbf8\uc0ac\uc77c \ud504\ub85c\uadf8\ub7a8\uacfc \uad6d\uc81c\ubc95\uc5d0 \ubc18\ud558\ub294 \uc911\uad6d\uc758 \uac15\uc555\uc801 \ud589\ub3d9, \uc911\uad6d\uc758 \ub300\ub9cc \uc555\ubc15\uc5d0 \ub300\ud55c \uc6b0\ub824\ub97c \ubc18\uc601\ud568.",
        "3f68bb77-8421-4cc2-bfb1-fe5a2d5d96dd": "\ud55c\uacc4, \uc801\ud569 \ub610\ub294 \ubd80\uc801\ud569\ud55c \uc0ac\uc6a9 \uc601\uc5ed\uc744 \uacf5\uac1c\uc801\uc73c\ub85c \ubcf4\uace0\ud558\uae30\ub85c \uc57d\uc18d\u2023 \uae30\uc5c5\uc740 AI \uc2dc\uc2a4\ud15c\uc774 \uc57c\uae30\ud560 \uc218 \uc788\ub294 \uc0ac\ud68c\uc801 \uc704\ud5d8\uc5d0 \ub300\ud55c \uc5f0\uad6c\ub97c \uc6b0\uc120\uc2dc\ud558\uba70, \uc545\uc758\uc801 \ud3b8\uacac\uacfc \ucc28\ubcc4\uc744 \ud53c\ud558\uace0 \uac1c\uc778\uc815\ubcf4\ub97c \ubcf4\ud638\ud558\uae30 \uc704\ud55c \ub178\ub825\uc744 \uc57d\uc18d\u2023 \uae30\uc5c5\uc740 \uc8fc\uc694 \uc0ac\ud68c \ubb38\uc81c\uc5d0 \ub300\ucc98\ud558\uae30 \uc704\ud55c \uace0\uae09 AI \uc2dc\uc2a4\ud15c\uc744 \uac1c\ubc1c\u00b7\ubc30\ud3ec\ud558\uae30 \uc704\ud574 \uc804\ub150\ucd9c\ucc98 : \ubbf8\uad6d \ubc31\uc545\uad00",
        "869f4f6b-e0a1-40c8-bdef-d8fca1f283f9": "6 (10)63.5 (3)\uc778\uc801\uc790\uc6d0 \ubc0f \uc5f0\uad6c202366.9 (1) 56.5 (12)\uc778\ud504\ub77c202360.6 (11)56.7 (25)\uc9c0\uc2dd \ubc0f \uae30\uc220 \uc0dd\uc0b0202353.3 (11)63.7 (2)\ucc3d\uc870\uc801 \uc0dd\uc0b0 202358.2 (5) 53.0 (12)\ucd9c\ucc98 : World Bank, IMF, \uad6d\uc81c\uc804\uae30\ud1b5\uc2e0\uc5f0\ud569(ITU), \uc138\uacc4\uc9c0\uc801\uc7ac\uc0b0\uad8c\uae30\uad6c(WIPO)",
        "358c6d47-5743-4799-834b-c6b4b65643c7": "9%)\ubcf4\ub2e4 \ub192\uc740 3.1%\ub97c \uae30\ub85d\ud558\uc5ec \uc5f0\uc900 \uace0\uc704\uc778\uc0ac\ub4e4\uc740 \uae30\uc900\uae08\ub9ac \uc778\ud558\uc5d0 \ub300\ud574 \uc2e0\uc911\ud55c \uc785\uc7a5\uc744 \ud45c\uba85\ud568[\ud45c 1] \ubbf8\uad6d ICT \uad6d\uac00 \uac1c\ud669\uad6c\ubd84 \uae30\uc900\ub144\ub3c4\ud55c\uad6d \ubbf8\uad6d\n\uc77c\ubc18\uac1c\ud669\n\uc778\uad6c 20235,150\ub9cc 5,000\uba853\uc5b5 3,669\ub9cc \uba85\uba74\uc801(1,000ha)202310,043983,151\uc5b8\uc5b4 2023\ud55c\uad6d\uc5b4\uc601\uc5b4, \uc2a4\ud398\uc778\uc5b4\uc885\uad50 2023\uae30\ub3c5\uad50, \ubd88\uad50 \ub4f1 \uac1c\uc2e0\uad50, \uac00\ud1a8\ub9ad \ub4f1\uc815\ubd80\ud615\ud0dc / \uc758\ud68c\uc81c\ub3c42023\ub300\ud1b5\ub839\uc81c / \ub2e8\uc6d0\uc81c\ub300\ud1b5\ub839\uc81c / \uc591\uc6d0\uc81c\n\uacbd\uc81c\ud604\ud669GDP 20231.70\uc870 \ub2ec\ub7ec27.97\uc870 \ub2ec\ub7ec\uacbd\uc81c \uc131\uc7a5\ub96020231.31%1.5%S&P \uc2e0\uc6a9\ub4f1\uae092023AA AA+\nICT\ud604\ud669\uc774\ub3d9\uc804\ud654 \uac00\uc785\uc790 \uc218 2022149\uba85(100\uba85\ub2f9) 110\uba85(100\uba85\ub2f9)\uc774\ub3d9\ud1b5\uc2e0 \uac00\uc785\uc790 \uc218 2022120\uba85(100\uba85\ub2f9) 174\uba85(100\uba85\ub2f9)\uc720\uc120 \ube0c\ub85c\ub4dc\ubc34\ub4dc \uac00\uc785\uc790 \uc218 202245\uba85(100\uba85\ub2f9) 38\uba85(100\uba85\ub2f9)\uc778\ud130\ub137 \uc0ac\uc6a9\uc790 \ube44\uc911202297%97%\n\uae00\ub85c\ubc8c\ud601\uc2e0\uc9c0\uc218\n\ucd1d\uc810 (\uc21c\uc704) 202358.6 (10)63.5 (3)\uc778\uc801\uc790\uc6d0 \ubc0f \uc5f0\uad6c202366.9 (1) 56.5 (12)\uc778\ud504\ub77c202360.6 (11)56.7 (25)\uc9c0\uc2dd \ubc0f \uae30\uc220 \uc0dd\uc0b0202353.3 (11)63.7 (2)\ucc3d\uc870\uc801 \uc0dd\uc0b0 202358.2 (5) 53.",
        "8b180cec-b912-44c5-8348-836b38e56ee8": "\ubc95\uc801, \uc0ac\ud68c\uc801 \uc601\ud5a5\uc5d0 \ub300\ud55c \uc774\ud574 \ubc0f \ub300\uc751: AI \uc2dc\uc2a4\ud15c\uc774 \uad6d\uac00\uc758 \uac00\uce58\ub97c \ubc18\uc601\ud558\uace0 \ud615\ud3c9\uc131\uc744 \uc99d\uc9c4\ud560 \uc218 \uc788\ub3c4\ub85d AI\uac00 \ucd08\ub798\ud558\ub294 \uc704\ud5d8\uc744 \uc774\ud574\ud558\uace0 \uc644\ud654\ud558\uae30 \uc704\ud55c \uc811\uadfc\ubc95 \uac1c\ubc1c\u2463 AI \uc2dc\uc2a4\ud15c\uc758 \uc548\uc804\uacfc \ubcf4\uc548 \ud655\ubcf4: \uc2e0\ub8b0\ud560 \uc218 \uc788\uc73c\uba70 \uc548\uc804\ud55c AI \uc2dc\uc2a4\ud15c\uc744 \uc124\uacc4\ud558\ub294 \ubc29\ubc95\uc5d0 \ub300\ud55c \uc9c0\uc2dd\uc744 \ubc1c\uc804\u2464 AI \ud559\uc2b5 \ubc0f \ud14c\uc2a4\ud2b8\ub97c \uc704\ud55c \uacf5\uc720 \uacf5\uac1c \ub370\uc774\ud130\uc640 \uc81c\ubc18 \ud658\uacbd \uad6c\ucd95: \uace0\ud488\uc9c8 \ub370\uc774\ud130 \uc14b\uacfc \ud658\uacbd, \ud14c\uc2a4\ud2b8 \ubc0f \uad50\uc721 \uc790\uc6d0\uc5d0 \ub300\ud55c \uc811\uadfc\uc744 \ud655\ub300\u2465 \ud45c\uc900\uacfc \ubca4\uce58\ub9c8\ud06c\ub97c \ud1b5\ud55c AI \uc2dc\uc2a4\ud15c \uce21\uc815 \ubc0f \ud3c9\uac00: AI \uad8c\ub9ac\uc7a5\uc804\uc744 \uc704\ud55c \uccad\uc0ac\uc9c4\uacfc AI \uc704\ud5d8 \uad00\ub9ac \ud504\ub808\uc784\uc6cc\ud06c\uc5d0 \ub530\ub77c \uae30\uc220 \ud45c\uc900 \ubc0f \ubca4\uce58\ub9c8\ud06c\ub97c \ud3ec\ud568\ud55c \uad11\ubc94\uc704\ud55c AI \ud3c9\uac00 \uae30\ubc95\uc744 \uac1c\ubc1c\u2466 \uad6d\uac00 AI R&D \uc778\ub825 \uc218\uc694\uc5d0 \ub300\ud55c \uc774\ud574 \uc81c\uace0: AI \uc778\ub825\uc744 \uc804\ub7b5\uc801\uc73c\ub85c \uc721\uc131\ud558\uae30 \uc704\ud574 R&D \uc778\ub825 \uac1c\ubc1c \uae30\ud68c\ub97c \uac1c\uc120\u2467 AI \ubc1c\uc804 \uac00\uc18d\ud654\ub97c \uc704\ud55c \uacf5\uacf5-\ubbfc\uac04 \ud30c\ud2b8\ub108\uc2ed \ud655\ub300: \ud559\uacc4, \uc0b0\uc5c5\uacc4,",
        "5ef01885-7b58-4752-bd00-5f13f6dd95c4": "\uc719\uc740 \ubbf8\uad6d \ub0b4\uc5d0\uc11c \ub4dc\ub860 \ubc30\uc1a1 \uc11c\ube44\uc2a4\ub97c \ud655\uc7a5\ud558\uc5ec \ubc30\uc1a1 \uc2dc\uac04\uc744 \ub2e8\ucd95\ud558\uace0 \ud658\uacbd\uc5d0 \ubbf8\uce58\ub294 \uc601\ud5a5\uc744 \uc904\uc774\uace0\uc790 \ud568\n FAA \uaddc\uc81c \uc644\ud654\ub85c \ub4dc\ub860 \ubc30\uc1a1 \uc2dc\uc7a5 \uc804\ub9dd \ubc1d\uc544\u2022 \ubbf8\uad6d \uc5f0\ubc29\ud56d\uacf5\uccad(Federal Aviation Administration, FAA)\uc740 \uc9d1\ub77c\uc778\uacfc \uac19\uc740 \uae30\uc5c5\ub4e4\uc5d0\uac8c \ube44\uac00\uc2dc\uad8c \ub4dc\ub860 \uc6b4\uc601(Beyond Visual Line of Sight, BVLOS)\uc5d0 \ub300\ud55c \uba74\uc81c\ub97c \ubd80\uc5ec\ud568\uc73c\ub85c\uc368 \ub4dc\ub860 \ubc30\uc1a1 \uc2dc\uc7a5\uc758 \uc131\uc7a5\uc744 \ucd09\uc9c4\ud558\uace0 \uc788\uc74c. \uc774\ub7ec\ud55c \uaddc\uc81c \uc644\ud654\ub294 \ub4dc\ub860 \ubc30\uc1a1 \uae30\uc220\uc758 \uc0c1\uc5c5\uc801 \ud65c\uc6a9 \uac00\ub2a5\uc131\uc744 \ub192\uc774\uba70, \ub354 \ub113\uc740 \uc9c0\uc5ed\uc5d0\uc11c \ub354 \ub9ce\uc740 \uace0\uac1d\uc5d0\uac8c \uc11c\ube44\uc2a4\ub97c \uc81c\uacf5\ud560 \uc218 \uc788\ub294 \uae38\uc744 \uc5f4\uc5b4\uc90c\u2022 FAA\uc758 \uaddc\uc81c \uc644\ud654\uc640 \uae30\uc220 \ubc1c\uc804\uc740 \ub4dc\ub860 \ubc30\uc1a1\uc774 \ubbf8\uad6d \uc804\uc5ed\uc5d0\uc11c \ud604\uc2e4\ud654\ub420 \uc218 \uc788\ub294 \uae30\ubc18\uc744 \ub9c8\ub828\ud568. \uc9d1\ub77c\uc778 \ubc0f \uc719\uacfc \uac19\uc740 \uae30\uc5c5\ub4e4\uc740 \uc774\ubbf8 \ubbf8\uad6d \ub0b4 \uc5ec\ub7ec \ub3c4\uc2dc\uc5d0\uc11c \uc2dc\ubc94 \uc6b4\uc601\uc744 \uc131\uacf5\uc801\uc73c\ub85c \uc218\ud589\ud558\uace0 \uc788\uc73c\uba70, \uc774\ub7ec\ud55c \ubc1c\uc804\uc740 \ub4dc\ub860 \ubc30\uc1a1\uc774 \ud658\uacbd\uc5d0 \ubbf8\uce58\ub294 \uc601\ud5a5\uc744 \uc904\uc774\uace0 \ubc30\uc1a1 \uacfc\uc815\uc758 \ud6a8\uc728\uc131\uc744 \ub192\uc774\ub294 \ub370 \uae30\uc5ec\ud560 \uac83\uc73c\ub85c \uae30\ub300\ub428",
        "7fdb00aa-4150-4a60-9104-3a6955215b2c": "11 \n\u2160. ICT \uad6d\uac00 \uc0b0\uc5c5 \ud604\ud669 3.ICT \uc8fc\uc694\uc815\ucc45  \u2462 \uad6d\uac00 AI R&D \uc804\ub7b5 \uacc4\ud68d\n \ucc45\uc784 \uc788\ub294 AI R&D \ud22c\uc790\ub97c \uc704\ud55c \uad6d\uac00 \uc804\ub7b5 \u2022 2023\ub144 5\uc6d4 \ubbf8\uad6d \uacfc\ud559\uae30\uc220\uc815\ucc45\uad6d(OSTP)\uc740 \ucc45\uc784 \uc788\ub294 AI R&D \ud22c\uc790\ub97c \uc704\ud55c \u2018\uad6d\uac00 AI R&D \uc804\ub7b5 \uacc4\ud68d(National AI R&D Strategic Plan)\u2019 \uc5c5\ub370\uc774\ud2b8\ub97c \ubc1c\ud45c\ud568\u2022 \uad6d\uac00 AI R&D \uc804\ub7b5 \uacc4\ud68d\uc740 9\ub300 \uc804\ub7b5\uc73c\ub85c \uc774\ub8e8\uc5b4\uc838 \uc788\uc73c\uba70, \uadf8 \ub0b4\uc6a9\uc740 \uc774\ud558\uc640 \uac19\uc74c\u2460 \ucc45\uc784 \uc788\ub294 AI \uc5f0\uad6c\uc5d0 \ub300\ud55c \uc7a5\uae30 \ud22c\uc790: AI \ubd84\uc57c \uae00\ub85c\ubc8c \ub9ac\ub354\uc2ed \ud655\ubcf4\uc640 \uacf5\uc775\uc5d0 \uae30\uc5ec\ud558\ub294 \ucc45\uc784 \uc788\ub294 \ud601\uc2e0\uc744 \uc704\ud574 \uc0dd\uc131\ud615 AI \ub4f1 \ucc28\uc138\ub300 AI\uc5d0 \ub300\ud55c \ud22c\uc790\ub97c \uc6b0\uc120\u2461 \uc778\uac04\uacfc AI\uc758 \ud611\uc5c5\uc744 \uc704\ud55c \ud6a8\uacfc\uc801\uc778 \ubc29\ubc95 \uac1c\ubc1c: \uc778\uac04\uc758 \ub2a5\ub825\uc744 \ud6a8\uacfc\uc801\uc73c\ub85c \ubcf4\uc644\ud558\ub294 AI \uc2dc\uc2a4\ud15c\uc744 \ub9cc\ub4dc\ub294 \ubc29\ubc95\uc5d0 \ub300\ud55c \uc774\ud574 \uc81c\uace0\u2462 AI\uc758 \uc724\ub9ac\uc801, \ubc95\uc801,",
        "2068b7d4-9960-4fdd-839c-8b819ee3f008": "\uc5ec\uae30\uc5d0\ub294 \uc548\uc804\ud558\uace0 \ucc45\uc784\uc788\ub294 AI \uacf5\uc720 \uc6d0\uce59\uc744 \ubc1c\uc804\uc2dc\ud0a4\ub294 \ub370 \uc911\uc810\uc744 \ub454 \uc591\uc790 AI \uac70\ubc84\ub10c\uc2a4 \uc6cc\ud0b9\uadf8\ub8f9\uc758 \uc124\ub9bd\uc774 \ud3ec\ud568\ub428. \ub610\ud55c, \uacf5\ub3d9 \uc5f0\uad6c \ubc0f \uad50\uc721 \uc790\uae08 \uc9c0\uc6d0\uc744 \ud1b5\ud55c \ubbf8\uad6d \uad6d\ub9bd\uacfc\ud559\uc7ac\ub2e8(NSF)\uacfc AI \uc2f1\uac00\ud3ec\ub974(AISG)\uc758 \ud611\uc5c5\uc740 \uc0c1\ud638 \uae30\uc220 \ubc1c\uc804\uacfc \uc548\uc804\uc5d0 \ub300\ud55c \ud5cc\uc2e0\uc744 \uac15\uc870\ud568\n EU\uc640 \uc0ac\uc774\ubc84 \ubcf4\uc548 \ud611\ub825 \uc99d\uc9c4\u2022 \ube0c\ub93c\uc140\uc5d0\uc11c \uc5f4\ub9b0 \uc81c9\ucc28 EU-\ubbf8\uad6d \uc0ac\uc774\ubc84 \ub300\ud654\ub294 EU\uc640 \ubbf8\uad6d \uac04\uc758 \ud0c4\ub825\uc801\uc778 \uc0ac\uc774\ubc84 \ubcf4\uc548 \ud30c\ud2b8\ub108\uc2ed\uc744 \uac15\ud654\ud558\ub294 \uc911\uc694\ud55c \ub2e8\uacc4\uc784. \uc591\uce21\uc740 \uac1c\ubc29\uc801\uc774\uace0 \uc0c1\ud638 \uc6b4\uc6a9 \uac00\ub2a5\ud55c \uc778\ud130\ub137\uacfc \uc0ac\uc774\ubc84 \uacf5\uac04\uc758 \uc548\uc815\uc131\uc5d0 \ub300\ud574 \ub17c\uc758\ud568. \uc774 \ub300\ud654\ub294 \uc545\ud654\ub41c \uae00\ub85c\ubc8c \uc0ac\uc774\ubc84 \uc704\ud611 \ud658\uacbd\uc5d0 \uc9c1\uba74\ud55c \ub300\uc11c\uc591 \uac04 \ud611\ub825\uacfc \uc870\uc728\uc744 \uc785\uc99d\ud558\ub294 \uac83\uc73c\ub85c, \uc0ac\uc774\ubc84 \ubcf4\uc548\uc5d0 \ub300\ud55c EU-\ubbf8\uad6d \uac04 \ud611\ub825\uc758 \uc2ec\ud654 \ud544\uc694\uc131\uc744 \uac15\uc870\ud568\u2022 \uc0ac\uc774\ubc84 \ub300\ud654 \uacfc\uc815\uc5d0\uc11c \uc720\ub7fd\uc5f0\ud569 \uc0ac\uc774\ubc84\ubcf4\uc548\uccad(ENISA)\uacfc \ubbf8\uad6d \uc0ac\uc774\ubc84\ubcf4\uc548 \ubc0f \uc778\ud504\ub77c \ubcf4\uc548\uccad (CISA)\uc740 \uc778\uc2dd\uacfc \ud6c8\ub828, \uc6b0\uc218 \uc0ac\ub840 \uad50\ud658, \uacf5\ub3d9 \uc0c1\ud669 \uc778\uc2dd\uc744 \uc704\ud55c \uc9c0\uc2dd \uacf5\uc720 \ub4f1\uc744 \uc8fc\uc81c\ub85c \uc6cc\ud0b9 \uc5b4\ub808\uc778\uc9c0\uba3c\ud2b8\ub97c \uacf5\uc2dd\ud654\ud568.",
        "b26d8e44-ebe7-4877-b02e-62fb71caa5c3": "\uc774 \ud30c\ud2b8\ub108\uc2ed\uc740 IBM\uc758 \ud074\ub77c\uc6b0\ub4dc \uc778\ud504\ub77c\uc640 watsonx.ai \uad6c\uc131 \uc694\uc18c\ub97c \ud65c\uc6a9\ud558\uc5ec \uc704\uc131\uc5d0 AI \ubaa8\ub378\uc744 \uc9c1\uc811 \uc6d0\ud074\ub9ad\uc73c\ub85c \ubc30\ud3ec\ud560 \uc218 \uc788\uac8c \ud568. \uc6b0\uc8fc\uc5d0\uc11c \ub370\uc774\ud130 \uc778\uc0ac\uc774\ud2b8\ub97c \ucc98\ub9ac\ud568\uc73c\ub85c\uc368, \uc9c0\uc0c1 \uc2dc\uc2a4\ud15c\uc5d0 \ub300\ud55c \uc758\uc874\ub3c4\ub97c \ud06c\uac8c \uc904\uc774\uace0 \ud1b5\uc2e0 \uc778\ud504\ub77c\uc5d0\uc11c \uc0c1\ub2f9\ud55c \ube44\uc6a9 \uc808\uac10\uc744 \uc81c\uacf5\ud568\u2022 IBM\uc740 \uc544\uba54\ub9ac\uce78 \ud0c0\uc6cc(American Tower)\uc640 \ud611\ub825\ud558\uc5ec \uc6b0\uc8fc\ub97c \ud3ec\ud568\ud55c \uc5d0\uc9c0\uc5d0\uc11c \ud558\uc774\ube0c\ub9ac\ub4dc \uba40\ud2f0 \ud074\ub77c\uc6b0\ub4dc \ud50c\ub7ab\ud3fc\uc758 \ubc30\uce58\ub97c \uac00\uc18d\ud654\ud568. IBM\uc758 \ud558\uc774\ube0c\ub9ac\ub4dc \ud074\ub77c\uc6b0\ub4dc \uae30\ub2a5\uc744 \uc544\uba54\ub9ac\uce78 \ud0c0\uc6cc\uc758 \ub514\uc9c0\ud138 \uc778\ud504\ub77c\uc640 \ud1b5\ud569\ud568\uc73c\ub85c\uc368, \ub370\uc774\ud130 \uc0dd\uc131 \uc9c0\uc810\uc5d0 \ub354 \uac00\uae4c\uc6b4 \uacf3\uc5d0\uc11c \ub370\uc774\ud130\ub97c \ucc98\ub9ac\ud558\uace0 \ubd84\uc11d\ud560 \uc218 \uc788\uac8c \ud558\uc5ec \uc9c0\uc5f0 \uc2dc\uac04\uc744 \uc904\uc77c \uac83\uc73c\ub85c \uae30\ub300\ub428",
        "27d448f7-b1fd-4aff-8c4d-10ecd13d76c8": "\u20181\uc870 \ub2ec\ub7ec \ud074\ub7fd(The Trillion Dollar Club)\u2019 \uae30\uc5c5\ub4e4\uc740 \ubbf8\uad6d\uacfc \uae00\ub85c\ubc8c \uc99d\uc2dc\ub97c \uc8fc\ub3c4\ud558\uace0 \uc788\uc74c\n[\ud45c 9] \ubbf8\uad6d \uc8fc\uc694 ICT \uae30\uc5c5 TOP10\uc21c\uc704 \uae30\uc5c5\uba85\uc2dc\uac00\ucd1d\uc561(\ub2ec\ub7ec) \uc0ac\uc5c5 \ubd84\uc57c\u2460 Microsoft(www.microsoft.com)3.029T\uac80\uc0c9\uc5d4\uc9c4, \ud074\ub77c\uc6b0\ub4dc \uc194\ub8e8\uc158 \ub4f1 \uc18c\ud504\ud2b8\uc6e8\uc5b4 \ubc0f IT \uc11c\ube44\uc2a4\u2461 Apple(www.apple.com)2.801T\uae30\uc220 \ud558\ub4dc\uc6e8\uc5b4 \ubc0f \uc18c\ud504\ud2b8\uc6e8\uc5b4\u2462 NVIDIA(www.nvidia.com)1.941T\ubc18\ub3c4\uccb4, \uadf8\ub798\ud53d \ud504\ub85c\uc138\uc11c \ubc0f \uce69\uc14b\u2463 Amazon(www.amazon.com)1.798T\uc804\uc790\uc0c1\uac70\ub798\u2464 Alphabet(www.alphabet.com)1.701T\uac80\uc0c9\uc5d4\uc9c4, \ud074\ub77c\uc6b0\ub4dc \uc194\ub8e8\uc158 \ub4f1 \uc18c\ud504\ud2b8\uc6e8\uc5b4 \ubc0f IT \uc11c\ube44\uc2a4\u2465 Meta Platforms(meta.com)1.233T\uc18c\ud504\ud2b8\uc6e8\uc5b4 \ubc0f IT \uc11c\ube44\uc2a4, \uc778\ud130\ub137, \uba54\ud0c0\ubc84\uc2a4\u2466 Broadcom(www.broadcom.com)597.54B\ubc18\ub3c4\uccb4, \uc778\ud504\ub77c \uc18c\ud504\ud2b8\uc6e8\uc5b4\u2467 Oracle(www.oracle.com)306.99B\ud074\ub77c\uc6b0\ub4dc \ucef4\ud4e8\ud305\u2468 Salesforce(www.salesforce.com)290.17B\ud074\ub77c\uc6b0\ub4dc \ucef4\ud4e8\ud305\u2469 AMD(www.amd.com)285.25B\ub9c8\uc774\ud06c\ub85c\ud504\ub85c\uc138\uc11c, \uce69\uc14b, \uadf8\ub798\ud53d \uce69 \ubc0f SoC(\uc2dc\uc2a4\ud15c \uc628 \uce69) \uc194\ub8e8\uc158\ucd9c\ucc98 : Companies Marketcap",
        "a34a0907-4d89-4f7f-a48a-99541d908ab9": "\uadf8\ub9ac\uace0 \ubbfc\uac04 \ubc0f \uacf5\uacf5 \ubd80\ubb38 \uac04 \uc2a4\ud399\ud2b8\ub7fc \uc758\uc0ac \uacb0\uc815\uc5d0 \ub300\ud55c \uc870\uc815\ub825 \uac1c\uc120-\ud63c\uc7a1 \ub300\uc5ed\uc758 \uc0ac\uc6a9\uc744 \uac15\ud654\ud558\uae30 \uc704\ud55c \ub2e4\uc774\ub098\ubbf9 \uc2a4\ud399\ud2b8\ub7fc \uc250\uc5b4\ub9c1 \uae30\ub2a5 \uac1c\ubc1c \ub4f1 \ucca8\ub2e8 \uae30\uc220\uc5d0 \uc911\uc810-\uad6d\uac00 \uc2a4\ud399\ud2b8\ub7fc \uc778\ub825 \uacc4\ud68d \uac1c\ubc1c\uc744 \ud1b5\ud574 \uc2a4\ud399\ud2b8\ub7fc \uc0dd\ud0dc\uacc4 \uc778\ub825 \uc591\uc131\u2022 \uad6d\uac00 \uc2a4\ud399\ud2b8\ub7fc \uc804\ub7b5\uc740 \uae30\uad00 \uac04 \uc870\uc815\uc744 \uac15\ud654\ud558\uace0, \ud601\uc2e0\uc744 \ucd09\uc9c4\ud558\uba70, \ud6a8\uc728\uc801\uc778 \uc2a4\ud399\ud2b8\ub7fc \uc0ac\uc6a9\uc744 \uc704\ud55c 4\uac00\uc9c0 \ucd95(pillar)\uc744 \uc81c\uc2dc\ud568[\ud45c 5] \uad6d\uac00 \uc2a4\ud399\ud2b8\ub7fc \uc804\ub7b5 4\uac00\uc9c0 \ucd95 \ubc0f \uc804\ub7b5 \ubaa9\ud45c\ucd95(Pillar) \uc804\ub7b5 \ubaa9\ud45c\n\u2460\ucca8\ub2e8 \ubc0f \uc2e0\ud765\uae30\uc220 \ubd84\uc57c\uc5d0\uc11c \ubbf8\uad6d\uc758 \ub9ac\ub354\uc2ed\uc744 \ud655\ubcf4\ud558\uae30 \uc704\ud55c \uc2a4\ud399\ud2b8\ub7fc \ud30c\uc774\ud504\ub77c\uc778\n1.1 \ud604\uc7ac\u00b7\ubbf8\ub798\uc758 \uc5f0\ubc29\uae30\uad00 \uc784\ubb34 \uc9c0\uc6d0\uc774 \uac00\ub2a5\ud55c \ucda9\ubd84\ud55c \uc2a4\ud399\ud2b8\ub7fc \uc811\uadfc\uc131 \ubcf4\uc7a51.2 \ud604\uc7ac\u00b7\ubbf8\ub798\uc758 \ubbfc\uac04 \ubd80\ubb38 \ud601\uc2e0\uc744 \uc9c0\uc6d0\ud560 \uc218 \uc788\ub3c4\ub85d \uc2a4\ud399\ud2b8\ub7fc \uc790\uc6d0 \ud655\ubcf41.3 \uc5f0\uad6c\ud560 \ucd94\uac00 \ub300\uc5ed\uc744 \uc2dd\ubcc4\ud558\uae30 \uc704\ud55c \uc9c0\uce68 \uc6d0\uce59 \ubc0f \uc120\ub3c4\uc801 \ud504\ub85c\uadf8\ub7a8 \uad00\ub9ac \uad00\ud589\uc744 \uc801\uc6a9\ud558\uc5ec \uc2a4\ud399\ud2b8\ub7fc \ud30c\uc774\ud504\ub77c\uc778 \uc720\uc9c0\n\u2461\uad6d\uac00\uc801 \uc2a4\ud399\ud2b8\ub7fc \uc694\uad6c\uc5d0 \ub300\uc751\ud558\uae30 \uc704\ud55c \ud611\ub825\uc801 \uc7a5\uae30\uacc4\ud68d\n2.",
        "76ec358d-ea7d-4809-8f41-e9b7af405d55": "\u2160 ICT \uad6d\uac00 \uc0b0\uc5c5 \ud604\ud669                   4   (*) SUMMARY   1. \uad6d\uac00 \uac1c\ud669   2. ICT \uc815\ubd80\uae30\uad6c   3. ICT \uc8fc\uc694 \uc815\ucc45   4. ICT \uc8fc\uc694 \ubc95\ub839 \ubc0f \uaddc\uc81c   5. ICT \uc8fc\uc694\uae30\uc5c5   6. \ud55c\uad6d \ud611\ub825 \ubc0f \uad6d\ub0b4\uae30\uc5c5 \uc9c4\ucd9c\uc0ac\ub840",
        "979d1acd-6fb1-4cf7-818c-ac37e53491ac": "GPT-4 \ud130\ubcf4\ub294 2023\ub144 4\uc6d4\uae4c\uc9c0\uc758 \uc9c0\uc2dd\uacfc \ud14d\uc2a4\ud2b8-\uc2a4\ud53c\uce58 \ud504\ub86c\ud504\ud2b8\uc640 \ud568\uaed8 \uc774\ubbf8\uc9c0\ub97c \uc785\ub825\uc73c\ub85c \ubc1b\uc544\ub4e4\uc77c \uc218 \uc788\ub294 \ub2a5\ub825\uc744 \ubcf4\uc5ec\uc8fc\uba70, \uc624\ud508AI\uac00 AI \ubaa8\ub378\uc758 \ub2e4\uc591\uc131\uacfc \uc801\uc6a9 \uac00\ub2a5\uc131\uc744 \uac15\ud654\ud558\ub824\ub294 \uc758\uc9c0\ub97c \ub4dc\ub7ec\ub0c4. \uc774\ub294 \uc81c\ubbf8\ub098\uc774 AI\ub97c \ubcf4\uc720\ud55c \uad6c\uae00\uc744 \ud3ec\ud568\ud55c \ub2e4\ub978 \ud68c\uc0ac\ub4e4\uc774 \uc624\ud508AI\uc758 \ud601\uc2e0\uc5d0 \ubc1c\ub9de\ucd94\uae30 \uc704\ud574 AI \uac1c\ubc1c \ub178\ub825\uc744 \uac00\uc18d\ud654 \ud558\ub3c4\ub85d \ucd09\ubc1c\ud568\n \ubbf8\uad6d \ub0b4 AI \ucc57\ubd07 \uae30\uc220\uc758 \ubbf8\ub798 \uc804\ub9dd \ubc0f \uc601\ud5a5  \u2022 \uad6c\uae00\uc758 \uc81c\ubbf8\ub098\uc774\uc640 \uc624\ud508AI\uc758 GPT \uc2dc\ub9ac\uc988\uc640 \uac19\uc740 AI \ubaa8\ub378\uc758 \ubc1c\uc804\uc740 \uc5ec\ub7ec \uc0b0\uc5c5 \uc804\ubc18\uc5d0 \uac78\uccd0 \ud601\uc2e0\uc744 \uc8fc\ub3c4\ud558\uace0 \uc788\uc73c\uba70, \ud2b9\ud788 \uc778\uac04\uacfc \uc720\uc0ac\ud55c \ubc18\uc751\uc744 \uc774\ud574\ud558\uace0 \uc0dd\uc131\ud558\ub294 \ub2a5\ub825\uc740 \uace0\uac1d \uc11c\ube44\uc2a4, \ucf58\ud150\uce20 \uc0dd\uc131, \uc2ec\uc9c0\uc5b4 \ud5ec\uc2a4\ucf00\uc5b4 \ubd84\uc57c\uc5d0\uc11c \ubcf4\ub2e4 \uc815\ud655\ud558\uace0 \ud6a8\uc728\uc801\uc778 \uc194\ub8e8\uc158\uc744 \uc81c\uacf5\ud560 \uac83\uc73c\ub85c \uae30\ub300\ub428\u2022 \uc774\ub7ec\ud55c \ubc1c\uc804\uc740 \uae30\uc220 \ud601\uc2e0\uc744 \ub118\uc5b4 \uace0\uc6a9 \uc2dc\uc7a5\uacfc \uacbd\uc81c\uc5d0\uae4c\uc9c0 \uc601\ud5a5\uc744 \ubbf8\uce68. AI \ucc57\ubd07\uc774 \uc77c\uc0c1\uc5d0 \ub354\uc6b1 \ud1b5\ud569\ub428\uc5d0 \ub530\ub77c \uc778\uac04 \uc0c1\ud638\uc791\uc6a9\uc5d0 \ud06c\uac8c \uc758\uc874\ud558\ub294 \ubd84\uc57c\uc5d0\uc11c \uc9c1\ubb34 \ubcc0\ub3d9\uc758 \uac00\ub2a5\uc131\uc774 \uc788\uc74c.",
        "e613a3cc-e9db-4dc2-b550-106085052a4f": "\ubbf8 \uad6d\ubc29\ubd80\ub294 \ub514\uc9c0\ud138 \ud2b8\uc708\uc774 \ub354 \ub9ce\uc740 \ub370\uc774\ud130\ub97c \ud3ec\ud568\ud558\uc5ec \uc758\uc0ac \uacb0\uc815 \uacfc\uc815\uc758 \uc815\ud655\ub3c4\uac00 \ub192\uc74c\uc5d0 \uc8fc\ubaa9\ud558\uc5ec \uad70\uc0ac \uc791\uc804\uc744 \uacc4\ud68d\ud558\uace0 \uc2e4\ud589\ud558\ub294\ub370 \uc911\uc2ec\uc801\uc778 \uc5ed\ud560\uc744 \ud560 \uac83\uc73c\ub85c \uae30\ub300\ud568\u2022 \uc704\uce58\ud0c0 \uc8fc\ub9bd\ub300\ud559\uad50 \uad6d\ub9bd \ud56d\uacf5 \uc5f0\uad6c\uc18c\uc640 \uac19\uc740 \ud559\uc220 \uae30\uad00\uacfc\uc758 \ud611\ub825\uc740 \uc804\ubb38 \uc9c0\uc2dd\uacfc \uc790\uc6d0\uc744 \ud1b5\ud574 \ub514\uc9c0\ud138 \ud2b8\uc708 \uac1c\ubc1c\uc774 \uac00\uc18d\ud654\ub418\ub294 \ubbf8\ub798\ub97c \uc608\uace0\ud568. \uc774\ub7ec\ud55c \ud611\ub825\uc740 \ud601\uc2e0\uc744 \ucd09\uc9c4\ud560 \ubfd0\ub9cc \uc544\ub2c8\ub77c \uad6d\ubc29\ubd80 \uc6b4\uc601\uc744 \uae30\uc220\uc801\uc73c\ub85c \uace0\ub3c4\ud654\ud558\uc5ec \ubbf8\uad6d\uc758 \uad70\uc0ac \uc900\ube44\uc131\uacfc \uc804\ub7b5\uc801 \ub2a5\ub825\uc744 \ub354\uc6b1 \uac15\ud654\ud560 \uac83\uc73c\ub85c \uae30\ub300\ub428",
        "507f88d8-89f1-4b21-ad4c-629909adbb56": "\uc0c1\ubb34\ubd80\ub294 \uc5ec\ub7ec \ud30c\ud2b8\ub108 \ubc0f \ub3d9\ub9f9\uad6d\uacfc \uae34\ubc00\ud55c \uc811\ucd09 \uc720\uc9c0\n\ubbf8\uad6d \uadfc\ub85c\uc790\ub97c \uc704\ud55c \uc77c\uc790\ub9ac \ubc0f \uc778\ub825 \ud30c\uc774\ud504\ub77c\uc778 \ucc3d\ucd9c\n\u2023 \ubc18\ub3c4\uccb4 \ubc0f \uae30\ud0c0 \uc0b0\uc5c5\uc5d0\uc11c \uc591\uc9c8\uc758 \uc77c\uc790\ub9ac\ub97c \ucc3d\ucd9c\ud560 \ud30c\uc774\ud504\ub77c\uc778 \uad6c\ucd95\uc744 \uc704\ud574 5\uac1c\uc758 \uc778\ub825 \ud5c8\ube0c \ucd08\uae30 \uc138\ud2b8 \ubc1c\ud45c\u2023 \ucd5c\uc18c 50\uac1c \uc774\uc0c1\uc758 \ucee4\ubba4\ub2c8\ud2f0 \ub300\ud559\uc5d0\uc11c \uc2e0\uaddc \ubc0f \ud655\uc7a5\ub41c \ubc18\ub3c4\uccb4 \uc778\ub825 \ud504\ub85c\uadf8\ub7a8 \ubc1c\ud45c\u2023 \uad6d\ub9bd\uacfc\ud559\uc7ac\ub2e8(NSF)\uc740 \uc81c\uc870 \uc778\ub825 \ubc0f \uc5f0\uad6c\uc790 \uc9c0\uc6d0, \ucee4\ub9ac\ud058\ub7fc \uac1c\ubc1c\uc5d0 \ucd08\uc810\uc744 \ub9de\ucd98 \uc0c8\ub85c\uc6b4 \uacc4\ud68d\uc744 \ud1b5\ud574 \ubbf8\uad6d \ubc18\ub3c4\uccb4 \uc778\ub825 \ud22c\uc790\u2023 \ubc18\ub3c4\uccb4 \uae30\uc5c5\uc758 \uc815\uaddc\uc9c1 \ucc44\uc6a9\uc5d0 \uc9c0\uc6d0\ud55c \ud559\uc0dd \uc218\ub294 2022~2023\ub144\uc5d0 79% \uc99d\uac00\n\ud601\uc2e0 \ud22c\uc790\u2023 \uc0c1\ubb34\ubd80\ub294 \uae30\ud0c0 \ubd80\ucc98\ub4e4\uacfc \uad6d\ub9bd \ubc18\ub3c4\uccb4 \uae30\uc220 \uc13c\ud130 \uc124\ub9bd \ucd94\uc9c4\u2023 \uc0c1\ubb34\ubd80\ub294 110\uc5b5 \ub2ec\ub7ec \uaddc\ubaa8\uc758 R&D \uc790\uae08\uc744 \uacc4\uce21 \ud504\ub85c\uadf8\ub7a8, \uad6d\ub9bd \uace0\uae09 \ud3ec\uc7a5 \uc81c\uc870 \ud504\ub85c\uadf8\ub7a8,",
        "66971a38-fce0-44f2-90b7-b7aef6db4f30": "6 \n\u2160. ICT \uad6d\uac00 \uc0b0\uc5c5 \ud604\ud669 2.ICT \uc815\ubd80\uae30\uad6c  \u2460 \uad6d\uac00\ud1b5\uc2e0\uc815\ubcf4\uad00\ub9ac\uccad(NTIA)\n \uad6d\uac00\ud1b5\uc2e0\uc815\ubcf4\uad00\ub9ac\uccad(NTIA)\u2022 \uc0c1\ubb34\ubd80 \uc0b0\ud558\uc758 \uad6d\uac00\ud1b5\uc2e0\uc815\ubcf4\uad00\ub9ac\uccad(National Telecommunications and Information Administration)\uc740 \uc8fc\ub85c \ud1b5\uc2e0 \ubc0f \uc815\ubcf4 \uc815\ucc45 \ubb38\uc81c\uc5d0 \ub300\ud558\uc5ec \ub300\ud1b5\ub839\uc5d0\uac8c \uc790\ubb38\uc744 \uc81c\uacf5\ud560 \ucc45\uc784\uc774 \uc788\ub294 \ud589\uc815 \uae30\uad00\uc784\u2022 \uad6d\uac00\ud1b5\uc2e0\uc815\ubcf4\uad00\ub9ac\uccad\uc740 \ucd5c\uadfc \u2018AI \uc5c5\ubb34\u2019, \u2018Open Weight AI \ubaa8\ub378\u2019 \ub4f1 AI \uad00\ub828 \uc815\ucc45 \uad8c\uc7a5 \uc0ac\ud56d \uac1c\ubc1c\uc744 \uc704\ud55c \ub300\uc911 \ucc38\uc5ec, \uc758\uacac \uc694\uccad \ub4f1\uc744 \uc2dc\uc791\ud568.",
        "2cea9d57-42c0-4ab4-9355-a70ddc5b91b6": "\uc5c5\uacc4\ub294 \uae30\uc220 \ubc1c\uc804\ubfd0\ub9cc \uc544\ub2c8\ub77c 6G\uc758 \uc2a4\ud399\ud2b8\ub7fc \uc694\uad6c\uc0ac\ud56d\uc744 \ud574\uacb0\ud558\uace0, \uae30\uc220\uc758 \uc804\uac1c\ub97c \uc9c0\uc6d0\ud558\ub294 \uaddc\uc81c\ub97c \uc639\ud638\ud558\uba70, \ubbf8\uad6d\uc774 \uad6d\uc81c\ubb34\ub300\uc5d0\uc11c \ud6a8\uacfc\uc801\uc73c\ub85c \uacbd\uc7c1\ud560 \uc218 \uc788\ub3c4\ub85d \ud558\ub294 \ub370 \uc911\uc810\uc744 \ub460\n \uae00\ub85c\ubc8c 6G \ud45c\uc900\ud654 \uacbd\uc7c1\uacfc \ubbf8\uad6d\uc758 \uc704\uce58 \u2022 \ubbf8\uad6d\uc740 \ub125\uc2a4\ud2b8 G \uc5bc\ub77c\uc774\uc5b8\uc2a4\uc758 \ub178\ub825\uc744 \ud1b5\ud574 \ud1b5\uc77c\ub41c \uae00\ub85c\ubc8c 6G \ud45c\uc900 \uac1c\ubc1c\uc5d0 \uc801\uadf9\uc801\uc73c\ub85c \ub178\ub825 \uc911\uc784. \uc774\ub294 \ubb34\uc120 \uae30\uc220\uc758 \ub2e8\ud3b8\ud654\ub97c \ubc29\uc9c0\ud558\uace0 \ud45c\uc900 \uc124\uc815 \uacfc\uc815\uc5d0\uc11c \ubbf8\uad6d \uae30\uc5c5\uc774 \ubc1c\uc5b8\uad8c\uc744 \uac16\ub294 \uac83\uc744 \ubcf4\uc7a5\ud558\ub294 \ub370 \ub9e4\uc6b0 \uc911\uc694\ud568\u2022 6G \ud45c\uc900 \uc124\uc815 \uacfc\uc815\uc5d0\uc11c \uc911\uad6d\uc5d0 \ub300\ud55c \uc6b0\ub824\ub294 \ubbf8\uad6d\uc758 \uacbd\uc7c1 \uae30\uc870 \uc720\uc9c0 \ub178\ub825\uc744 \uac15\ud654\ud568. \uc911\uad6d\uc758 \uc601\ud5a5\ub825\uc744 \uacbd\uacc4\ud55c \ubbf8\uad6d \ud1b5\uc2e0\uc5c5\uacc4\ub294 \uae00\ub85c\ubc8c \ud45c\uc900 \uc124\uc815 \uae30\uad00\uc5d0 \uc81c\ucd9c\ud560 \uc218 \uc788\ub294 \uad6d\ub0b4 \ubb34\uc120 \uae30\uc220\uc744 \uac1c\ubc1c\ud558\uae30 \uc704\ud574 \ub125\uc2a4\ud2b8 G \uc5bc\ub77c\uc774\uc5b8\uc2a4\ub97c \uc9c0\uc9c0\ud568. \uc774 \ub178\ub825\uc740 6G \ud45c\uc900\uc744 \ub9cc\ub4dc\ub294 \ub370 \ubbf8\uad6d\uc758 \ub450\ub4dc\ub7ec\uc9c4 \uc5ed\ud560\uc744 \ud655\ubcf4\ud558\uc5ec \ubbf8\uad6d\uc758 \ud601\uc2e0\uc774 \ud1b5\uc2e0\uc758 \ubbf8\ub798\ub97c \uacc4\uc18d \ud615\uc131\ud558\ub3c4\ub85d \ud558\ub294 \uac83\uc744 \ubaa9\ud45c\ub85c \ud568",
        "d998a04d-c777-43fa-9562-561130a9a3cb": "\uc9d1\ub77c\uc778\uc740 \uc774\ubbf8 \uc544\ud504\ub9ac\uce74\uc640 \ud638\uc8fc\uc5d0\uc11c \uc131\uacf5\uc801\uc778 \ubc30\uc1a1\uc744 \uc218\ud589\ud574\uc654\uc73c\uba70, \ubbf8\uad6d \ub0b4\uc5d0\uc11c\ub3c4 \uc774 \uae30\uc220\uc744 \ud1b5\ud574 \ub354 \ub9ce\uc740 \uace0\uac1d\uc5d0\uac8c \uc11c\ube44\uc2a4\ub97c \uc81c\uacf5\ud560 \uacc4\ud68d\uc784\u2022 \uc719(Wing)\uc740 \uc790\ub3d9\ud654\ub41c \uc719 \ubc30\uc1a1 \ub124\ud2b8\uc6cc\ud06c\ub97c \ubc1c\ud45c\ud558\uc600\uc73c\uba70, \uc774\ub294 \uc6b0\ubc84(Uber)\uac00 \uc6b4\uc804\uc790\ub97c \ubc30\uce58\ud558\ub294 \uac83\uacfc \uc720\uc0ac\ud55c \ubc29\uc2dd\uc73c\ub85c \ub4dc\ub860\uc744 \ud6a8\uc728\uc801\uc73c\ub85c \ubc30\uce58\ud558\uc5ec \ubb3c\ud488\uc744 \ubc30\uc1a1\ud568. \uc719\uc758 \uae30\uc220\uc740 \ubc30\uc1a1 \uacfc\uc815\uc744 \uc790\ub3d9\ud654\ud558\uace0 \ub4dc\ub860 \ubc30\uc1a1\uc758 \ud6a8\uc728\uc131\uacfc \uc548\uc804\uc131\uc744 \ub192\uc774\ub294 \ub370 \uc911\uc810\uc744 \ub460. \uc719\uc740 \ubbf8\uad6d \ub0b4\uc5d0\uc11c \ub4dc\ub860 \ubc30\uc1a1 \uc11c\ube44\uc2a4\ub97c \ud655\uc7a5\ud558\uc5ec \ubc30\uc1a1 \uc2dc\uac04\uc744 \ub2e8\ucd95\ud558\uace0 \ud658\uacbd\uc5d0 \ubbf8\uce58\ub294 \uc601\ud5a5\uc744 \uc904\uc774\uace0\uc790 \ud568\n FAA \uaddc\uc81c \uc644\ud654\ub85c \ub4dc\ub860 \ubc30\uc1a1 \uc2dc\uc7a5 \uc804\ub9dd \ubc1d\uc544\u2022 \ubbf8\uad6d \uc5f0\ubc29\ud56d\uacf5\uccad(Federal Aviation Administration, FAA)\uc740 \uc9d1\ub77c\uc778\uacfc \uac19\uc740 \uae30\uc5c5\ub4e4\uc5d0\uac8c \ube44\uac00\uc2dc\uad8c \ub4dc\ub860 \uc6b4\uc601(Beyond Visual Line of Sight, BVLOS)\uc5d0 \ub300\ud55c \uba74\uc81c\ub97c \ubd80\uc5ec\ud568\uc73c\ub85c\uc368 \ub4dc\ub860 \ubc30\uc1a1 \uc2dc\uc7a5\uc758 \uc131\uc7a5\uc744 \ucd09\uc9c4\ud558\uace0 \uc788\uc74c.",
        "b94e3a73-e60d-4460-af7c-a639af6f349e": "50\uc5b5 \ub2ec\ub7ec(\uc57d 6\uc870 2,400\uc5b5 \uc6d0) \uc774\uc0c1\uc758 \ucd08\uae30 \ud22c\uc790\ub85c, NSTC\ub294 \uad6d\uac00 \ubc18\ub3c4\uccb4 R&D \ub178\ub825\uc758 \ud575\uc2ec\uc774 \ub420 \uac83\uc73c\ub85c \uae30\ub300\ub428. \uc774 \ubbfc\uad00 \ucee8\uc18c\uc2dc\uc5c4\uc740 \ubc18\ub3c4\uccb4 \uae30\uc220 \ud601\uc2e0\uc744 \uc8fc\ub3c4\ud558\uace0, \ucd5c\ucca8\ub2e8 \ubc18\ub3c4\uccb4 \uae30\uc220\uc758 \uc124\uacc4, \ud504\ub85c\ud1a0\ud0c0\uc774\ud551, \uc2dc\ubc94 \uc6b4\uc601\uc744 \uc6a9\uc774\ud558\uac8c \ud558\ub294 \uc784\ubb34\ub97c \ub9e1\uace0 \uc788\uc74c\u2022 \uc774\uc678\uc5d0\ub3c4 CHIPS \ubc95\uc548\uc758 R&D \ud504\ub85c\uadf8\ub7a8\uc740 \uad6d\uac00 \ucca8\ub2e8 \ud3ec\uc7a5 \uc81c\uc870 \ud504\ub85c\uadf8\ub7a8(National Advanced Packaging Manufacturing Program) \ubc0f CHIPS \uc81c\uc870 USA \uc5f0\uad6c\uc18c(CHIPS Manufacturing USA Institute)\uc5d0 \ub300\ud55c \uc790\uae08 \uc9c0\uc6d0\uc744 \ud3ec\ud568\ud568. \uc774\ub7ec\ud55c \ud504\ub85c\uadf8\ub7a8\uc740 \ucca8\ub2e8 \ud3ec\uc7a5 \uae30\uc220\ubd80\ud130 \uc81c\uc870 \uacf5\uc815\uc758 \ub514\uc9c0\ud138 \ud2b8\uc708 \uae30\uc220 \uac1c\ubc1c\uc5d0 \uc774\ub974\uae30\uae4c\uc9c0 \ubc18\ub3c4\uccb4 \uc81c\uc870\uc758 \ud575\uc2ec \uce21\uba74\uc744 \ub2e4\ub8e8\uae30 \uc704\ud574 \uc124\uacc4\ub428. \uc774\ub97c \ud1b5\ud574, \ubbf8\uad6d \uc815\ubd80\ub294 \uc81c\uc870\uc5d0\ub9cc \ucd08\uc810\uc744 \ub9de\ucd94\uc9c0 \uc54a\uace0 \ubc18\ub3c4\uccb4 \uc0b0\uc5c5\uc5d0\uc11c \uc9c0\uc18d\uc801\uc778 \ub9ac\ub354\uc2ed\uc744 \uc720\uc9c0\ud558\uae30 \uc704\ud574 \ud544\uc694\ud55c \uc5f0\uad6c \ubc0f \uac1c\ubc1c\uc744 \uc6b0\uc120\uc2dc\ud558\ub294 \ud3ec\uad04\uc801\uc778 \uad6d\uac00 \uc804\ub7b5\uc758 \uae30\ubc18\uc744 \ub9c8\ub828\ud558\uace0 \uc788\uc74c",
        "e731ecb4-ae82-4c83-a30f-9655a26867c8": "3 \uc2a4\ud399\ud2b8\ub7fc \uc0ac\uc6a9\uc5d0 \ub300\ud55c \ud544\uc218 \ub370\uc774\ud130\uc640 \uc815\ubcf4\ub97c \ubaa8\uc73c\uae30 \uc704\ud574 \uc694\uad6c\uc0ac\ud56d\uc744          \uc815\uc758\ud558\uace0 \uae30\ub2a5\uc744 \uad6c\ud604\n\u2462\uae30\uc220 \uac1c\ubc1c\uc744 \ud1b5\ud55c \uc804\ub840 \uc5c6\ub294 \uc2a4\ud399\ud2b8\ub7fc \ud601\uc2e0, \uc811\uadfc \ubc0f \uad00\ub9ac\n3.1 \uc2e0\uae30\uc220 \ubc0f \uc2e0\ud765\uae30\uc220\uc5d0 \ub300\ud55c \ud22c\uc790\ub97c \ucd09\uc9c4\ud558\uc5ec \uc2a4\ud399\ud2b8\ub7fc \ud6a8\uc728\uc131\uc744 \uac1c\uc120\ud558\uace0     \uc0c1\uc0dd \ub3c4\ubaa83.2 \uc9d1\uc911\uc801\uc774\uace0 \uc815\uad50\ud55c \uc5f0\uad6c\uac1c\ubc1c(R&D)\uc744 \ud1b5\ud574 \uc804\uc790\uae30 \uc2a4\ud399\ud2b8\ub7fc\uc5d0 \ub300\ud55c \ucd1d\uccb4\uc801     \uc774\ud574 \ud5a5\uc0c1\uc5d0 \uc804\ub1503.3 \uc2a4\ud399\ud2b8\ub7fc\uc758 \uc720\uc5f0\ud55c \ud65c\uc6a9\uc744 \uadf9\ub300\ud654\ud558\uace0 \uc0c8\ub86d\uace0 \ud601\uc2e0\uc801\uc778 \uae30\uc220\uc744 \uc218\uc6a9\ud558\uba70,       \uc2a4\ud399\ud2b8\ub7fc \uc811\uadfc \ud655\ub300 \uae30\ud68c\ub97c \ubc1c\uad74\ud558\ub294 \uc2a4\ud399\ud2b8\ub7fc \uc815\ucc45 \ucd94\uad6c\n\u2463\uc2a4\ud399\ud2b8\ub7fc \uc804\ubb38\uc131 \ud655\ub300 \ubc0f \uad6d\uac00\uc801 \uc778\uc2dd \uc81c\uace04.1 \ud604\uc138\ub300\uc640 \ubbf8\ub798 \uc138\ub300\uc758 \uc2a4\ud399\ud2b8\ub7fc \uc778\ub825\uc744 \uc720\uc778\u00b7\uad50\uc721\u00b7\uc131\uc7a54.2 \uc2a4\ud399\ud2b8\ub7fc \uace0\ub824\uc0ac\ud56d\uc5d0 \ub300\ud55c \uc815\ucc45 \uc785\uc548\uc790\uc758 \uc774\ud574\ub97c \ud5a5\uc0c14.3 \ubb34\uc120 \uc8fc\ud30c\uc218 \uc2a4\ud399\ud2b8\ub7fc\uc5d0 \ub300\ud55c \ub300\uc911\uc758 \uc774\ud574\ub97c \ub192\uc774\uace0 \uc77c\uc0c1\uc0dd\ud65c\uc5d0\uc11c      \uc2a4\ud399\ud2b8\ub7fc\uc758 \uc5ed\ud560\uc5d0 \ub300\ud55c \uc778\uc2dd \uc81c\uace0\ucd9c\ucc98 : \ubbf8\uad6d \uad6d\uac00\ud1b5\uc2e0\uc815\ubcf4\uad00\ub9ac\uccad"
    },
    "relevant_docs": {
        "b3c2606c-0943-41ee-b08a-d79feebfb14d": [
            "69db4a2f-46a3-4db6-9a36-fc2f506a41ce"
        ],
        "51429fb0-516a-4a7d-a035-6984f7d236b2": [
            "69db4a2f-46a3-4db6-9a36-fc2f506a41ce"
        ],
        "38a5a9f9-3307-4ce4-8122-6a3294fcf867": [
            "553dcf19-20a0-4f5a-ae65-b5a67f7dfbc1"
        ],
        "dae4fd20-ae84-41eb-bbfe-164c215208bf": [
            "553dcf19-20a0-4f5a-ae65-b5a67f7dfbc1"
        ],
        "9ff4a22d-763e-4d85-8239-594e55e05f27": [
            "e46dbc1b-fbeb-48bd-9d7d-491cad4d6402"
        ],
        "ab4a35c3-b515-4896-91f8-3415bfa7fa7a": [
            "e46dbc1b-fbeb-48bd-9d7d-491cad4d6402"
        ],
        "eaf8eb0e-9291-4cb2-9f9d-07deba2e8af5": [
            "987a5ce8-467f-4096-97b6-d50d0beed5b9"
        ],
        "f75dd53a-296b-4aeb-bea5-22c354b8dae8": [
            "987a5ce8-467f-4096-97b6-d50d0beed5b9"
        ],
        "da98e0d4-d0c2-49e2-9aea-d8b41044dbc0": [
            "3a53f459-81b5-419f-90de-169710644f19"
        ],
        "eb9354e3-9ba5-4e58-b485-0da5ff03f7cb": [
            "3a53f459-81b5-419f-90de-169710644f19"
        ],
        "7823496a-eca4-4a2f-9790-02803c5b0e3e": [
            "f1e31416-85f0-498c-a531-948bba709eda"
        ],
        "5b6847b5-fc21-4871-8b9f-99059a5bd716": [
            "f1e31416-85f0-498c-a531-948bba709eda"
        ],
        "3934c613-791b-4cab-869d-fafba77fa4c3": [
            "b3c95e12-70c8-4038-a738-9575670c520e"
        ],
        "943ce69e-dfb1-4089-bc1f-9be61a38174b": [
            "b3c95e12-70c8-4038-a738-9575670c520e"
        ],
        "61b593cb-5a82-44c0-a896-092cce4a0cc1": [
            "6994870b-693b-47f5-aaf4-99a0ee0fceb8"
        ],
        "be428685-4eea-4903-ab1a-4efc5c02c826": [
            "6994870b-693b-47f5-aaf4-99a0ee0fceb8"
        ],
        "c8991089-7218-4825-a107-9f46425f35c2": [
            "e3cbe666-93f6-4d79-9fe9-36a30ab6c2df"
        ],
        "504c2007-3382-4934-bbf9-1149fe4919d3": [
            "e3cbe666-93f6-4d79-9fe9-36a30ab6c2df"
        ],
        "af36cebb-0fe4-4935-aa8f-c3d7a7b76632": [
            "ecbdc197-27df-41f0-b8be-a8fdf2767cf4"
        ],
        "ae82e4ab-b3e7-412f-87e9-6c38bab01ba7": [
            "ecbdc197-27df-41f0-b8be-a8fdf2767cf4"
        ],
        "af66c07c-fd53-4704-a075-9e61aeb5ad12": [
            "ac13f339-e077-4835-8eed-f363a7078293"
        ],
        "4ab9ddc1-1f04-4fb4-8aa4-aab80fc6ed0c": [
            "ac13f339-e077-4835-8eed-f363a7078293"
        ],
        "0ba1c99f-2b1c-427a-8317-e258aee9fba6": [
            "35e24ac0-4869-4a51-a060-75cc08ca3bd6"
        ],
        "9740bcc2-b0cc-46ae-bdaa-a663aec63481": [
            "35e24ac0-4869-4a51-a060-75cc08ca3bd6"
        ],
        "1ef27f55-708d-417d-a4d3-33b43a0d57cc": [
            "798ad9fd-61ec-4efb-a048-bc3c185968b6"
        ],
        "304cc47d-15ea-4924-8842-464140f3fd93": [
            "798ad9fd-61ec-4efb-a048-bc3c185968b6"
        ],
        "d5c4fc6f-b08e-4d25-b3f1-4f0809e9b566": [
            "1101237d-9eab-45c0-a655-ba619a882322"
        ],
        "222cf99c-408f-44db-9039-0215cf354c23": [
            "1101237d-9eab-45c0-a655-ba619a882322"
        ],
        "6996bede-e241-4c9e-a248-96e60ae138eb": [
            "99e80918-fac0-4a22-bb42-b9d87d8505b0"
        ],
        "68e6e800-d7c9-4d1e-b1c4-c348b0c17154": [
            "99e80918-fac0-4a22-bb42-b9d87d8505b0"
        ],
        "8aa2f8f0-9aed-4be3-b3b8-841f53465d6d": [
            "1e29e1e5-089e-4703-a6ac-95e6a2584435"
        ],
        "2a6ec816-9382-426f-b899-8167699d985a": [
            "1e29e1e5-089e-4703-a6ac-95e6a2584435"
        ],
        "625a9768-82f0-45ae-8d2a-16a0d7c89dd9": [
            "67a9e33e-5f42-4bf6-86f5-a5509dcf9033"
        ],
        "31a37ef4-4fa2-4cbb-8bde-8d9b4f52986d": [
            "67a9e33e-5f42-4bf6-86f5-a5509dcf9033"
        ],
        "dc89c197-0e6f-4aff-88a4-9dbd7b1dbb7f": [
            "19ef3369-ef4e-413f-b0a3-f1ddec2a8b6e"
        ],
        "2c87ae69-72e9-4b3e-9dea-abbf6b30a0bd": [
            "19ef3369-ef4e-413f-b0a3-f1ddec2a8b6e"
        ],
        "888a71b0-79b7-4179-b29f-9569493e592f": [
            "67a11feb-e62c-4821-8fbc-c97cc7df6e4a"
        ],
        "b86a38b5-f35a-41eb-a318-04ca660ff320": [
            "67a11feb-e62c-4821-8fbc-c97cc7df6e4a"
        ],
        "79a2b5ce-0d23-4ff5-a36f-feabae961e14": [
            "80b5de65-d555-4194-90d8-18f499516714"
        ],
        "872fdd77-1dde-401f-afc5-1ddae0129aae": [
            "80b5de65-d555-4194-90d8-18f499516714"
        ],
        "a3620ae1-833e-4e70-bf25-78b9ab1750e4": [
            "a21fff63-441e-4cb3-8295-119d0308d2a4"
        ],
        "f0c04dc6-d67b-4854-aba1-20e7abb0b5bd": [
            "a21fff63-441e-4cb3-8295-119d0308d2a4"
        ],
        "5768d6b8-d7df-4aea-a07d-a8d032751d34": [
            "df5bc443-f027-4ea5-8ab2-6aa26ab5f469"
        ],
        "a198bb63-2b2e-4e97-80cc-5a2cdfb4e2fa": [
            "df5bc443-f027-4ea5-8ab2-6aa26ab5f469"
        ],
        "80caed2e-d888-498d-b048-6ebcdea14e8b": [
            "0157601f-ca05-439b-9bc6-83869ba59d26"
        ],
        "a41a2f3a-cf4b-4509-bc10-355e17b5d926": [
            "0157601f-ca05-439b-9bc6-83869ba59d26"
        ],
        "8851aef7-577b-45a6-9caf-68af79034efc": [
            "3f68bb77-8421-4cc2-bfb1-fe5a2d5d96dd"
        ],
        "16e4da18-a1ef-4c9d-b63e-a43e87caeeb3": [
            "3f68bb77-8421-4cc2-bfb1-fe5a2d5d96dd"
        ],
        "0560d030-b474-4217-a6e2-570f981a3ba1": [
            "869f4f6b-e0a1-40c8-bdef-d8fca1f283f9"
        ],
        "d7ef023b-d17d-40c9-ad69-f8659cecc21e": [
            "869f4f6b-e0a1-40c8-bdef-d8fca1f283f9"
        ],
        "640935c5-8846-475b-af92-569883e00447": [
            "358c6d47-5743-4799-834b-c6b4b65643c7"
        ],
        "5472d595-0a35-4717-9cfc-31c187ffec01": [
            "358c6d47-5743-4799-834b-c6b4b65643c7"
        ],
        "afd04fbf-2661-468a-86dc-a9157f22f956": [
            "8b180cec-b912-44c5-8348-836b38e56ee8"
        ],
        "c6185dd3-2168-440f-954d-4410e2ecfca2": [
            "8b180cec-b912-44c5-8348-836b38e56ee8"
        ],
        "41ef2030-7cc9-49d2-9e5f-bc6a3eb00f5c": [
            "5ef01885-7b58-4752-bd00-5f13f6dd95c4"
        ],
        "4f4bad74-5e8f-4fbd-888e-89bb57124138": [
            "5ef01885-7b58-4752-bd00-5f13f6dd95c4"
        ],
        "60100f3e-670f-48df-b6d4-3826aa939b8f": [
            "7fdb00aa-4150-4a60-9104-3a6955215b2c"
        ],
        "ddbd8d90-8b2f-47fc-b664-55791a86b4b8": [
            "7fdb00aa-4150-4a60-9104-3a6955215b2c"
        ],
        "5d8cbf07-938b-4a36-a17d-1e8a0069ab80": [
            "2068b7d4-9960-4fdd-839c-8b819ee3f008"
        ],
        "07577b1e-df15-4509-84d3-47bbd3da0984": [
            "2068b7d4-9960-4fdd-839c-8b819ee3f008"
        ],
        "ff01a229-b58c-41a1-a881-adcb62ed3245": [
            "b26d8e44-ebe7-4877-b02e-62fb71caa5c3"
        ],
        "930130f3-0040-4cc9-b559-8809f2d22308": [
            "b26d8e44-ebe7-4877-b02e-62fb71caa5c3"
        ],
        "69ddf7bb-f997-4848-9a7f-e6b664f78df0": [
            "27d448f7-b1fd-4aff-8c4d-10ecd13d76c8"
        ],
        "1743f680-e71b-4ce3-b123-482370e1f937": [
            "27d448f7-b1fd-4aff-8c4d-10ecd13d76c8"
        ],
        "a4e977fa-70b1-40a9-821e-17ee62a3c88d": [
            "a34a0907-4d89-4f7f-a48a-99541d908ab9"
        ],
        "d7433a88-1bc8-47a0-b35e-af40081c75cc": [
            "a34a0907-4d89-4f7f-a48a-99541d908ab9"
        ],
        "1e0ae716-0056-4a43-a773-5be84aaf41f8": [
            "76ec358d-ea7d-4809-8f41-e9b7af405d55"
        ],
        "4077694f-07cc-4614-8e18-849264fc9a9a": [
            "76ec358d-ea7d-4809-8f41-e9b7af405d55"
        ],
        "732470f1-e43e-497d-b3b5-0af1ebce6916": [
            "979d1acd-6fb1-4cf7-818c-ac37e53491ac"
        ],
        "8368dd01-f73a-47c5-9ba1-f309cd3fea1d": [
            "979d1acd-6fb1-4cf7-818c-ac37e53491ac"
        ],
        "fe7bd2f7-f705-425c-8213-da97bcaba817": [
            "e613a3cc-e9db-4dc2-b550-106085052a4f"
        ],
        "13768bd7-972a-4b28-bcac-573fd3ee0d43": [
            "e613a3cc-e9db-4dc2-b550-106085052a4f"
        ],
        "7c9faa9d-9c94-43f1-bfe9-67d8a302764b": [
            "507f88d8-89f1-4b21-ad4c-629909adbb56"
        ],
        "863904bf-4b3b-4ee4-a5eb-9ed981331424": [
            "507f88d8-89f1-4b21-ad4c-629909adbb56"
        ],
        "945312a0-128f-45ce-9d95-1fd94c2fba42": [
            "66971a38-fce0-44f2-90b7-b7aef6db4f30"
        ],
        "45d40276-9d8e-4e28-84b3-4e9f5bc55ed9": [
            "66971a38-fce0-44f2-90b7-b7aef6db4f30"
        ],
        "56407032-e0dd-4255-8427-8d35fbdb469d": [
            "2cea9d57-42c0-4ab4-9355-a70ddc5b91b6"
        ],
        "05f254df-3de3-41bd-8756-0af0d86cfb40": [
            "2cea9d57-42c0-4ab4-9355-a70ddc5b91b6"
        ],
        "b87644ce-8ab8-4843-88db-f2ee89729359": [
            "d998a04d-c777-43fa-9562-561130a9a3cb"
        ],
        "36d941fb-3f63-467c-8613-9694a843a6fe": [
            "d998a04d-c777-43fa-9562-561130a9a3cb"
        ],
        "4261d372-a7b2-4eb8-8b03-eb080b63a27c": [
            "b94e3a73-e60d-4460-af7c-a639af6f349e"
        ],
        "460a861d-bf27-484d-97f7-aeeebc6b0a32": [
            "b94e3a73-e60d-4460-af7c-a639af6f349e"
        ],
        "8a658469-f774-4c9f-adff-6bef5d7e211d": [
            "e731ecb4-ae82-4c83-a30f-9655a26867c8"
        ],
        "f61af39c-17ab-455a-afa8-60cd4ce8be85": [
            "e731ecb4-ae82-4c83-a30f-9655a26867c8"
        ]
    },
    "mode": "text"
}